{
    "farm": {
        "b98091d788abdb8e62f9ca82f65786cd414db4a0": {
            "meaningful_joins": "yes",
            "table_exp_type": "INNER JOIN_INNER JOIN",
            "where_type": {
                "logical_operator": [
                    "OR",
                    "pattern_matching",
                    "exists_subquery"
                ]
            },
            "number_of_value_exp_in_group_by": 0,
            "having_type": "none",
            "orderby_type": "number_DESC",
            "limit_type": "without_offset",
            "value_exp_types": [
                "single_exp",
                "string_func_exp_alias"
            ],
            "distinct_type": "none",
            "min_max_depth_in_subquery": [
                3,
                5
            ]
        },
        "bd6b62343ad71e9e65b0d8b92aa739e94f5c9439": {
            "meaningful_joins": "yes",
            "table_exp_type": "FULL OUTER JOIN_FULL OUTER JOIN",
            "where_type": "exists_subquery",
            "number_of_value_exp_in_group_by": 5,
            "having_type": "none",
            "orderby_type": "number_DESC",
            "limit_type": "none",
            "value_exp_types": [
                "alias_exp",
                "single_exp"
            ],
            "distinct_type": "none",
            "min_max_depth_in_subquery": [
                3,
                5
            ]
        },
        "f1420b2d2fde379ea3a376e10818c057d346421a": {
            "meaningful_joins": "mixed",
            "table_exp_type": "LEFT JOIN",
            "where_type": {
                "logical_operator": [
                    "AND",
                    "between",
                    "comparison_with_subquery"
                ]
            },
            "number_of_value_exp_in_group_by": 0,
            "having_type": "none",
            "orderby_type": "ASC",
            "limit_type": "with_offset",
            "value_exp_types": [
                "agg_exp_alias"
            ],
            "distinct_type": "distinct",
            "min_max_depth_in_subquery": [
                3,
                5
            ]
        },
        "156769587d0c603fe5c876e467e4de8bc683c154": {
            "meaningful_joins": "yes",
            "table_exp_type": "FULL OUTER JOIN_Join",
            "where_type": {
                "logical_operator": [
                    "OR",
                    "pattern_matching",
                    "in_with_subquery"
                ]
            },
            "number_of_value_exp_in_group_by": 5,
            "having_type": "single",
            "orderby_type": "number_ASC",
            "limit_type": "none",
            "value_exp_types": [
                "string_func_exp"
            ],
            "distinct_type": "none",
            "min_max_depth_in_subquery": [
                3,
                5
            ]
        },
        "39aba8e6ff0216563e944e35d3e4171fd83b6a04": {
            "meaningful_joins": "yes",
            "table_exp_type": "INNER JOIN_Join",
            "where_type": {
                "logical_operator": [
                    "AND",
                    "pattern_matching",
                    "comparison_with_subquery"
                ]
            },
            "number_of_value_exp_in_group_by": 5,
            "having_type": "single",
            "orderby_type": "none",
            "limit_type": "with_offset",
            "value_exp_types": [
                "agg_exp_alias",
                "agg_exp_alias"
            ],
            "distinct_type": "none",
            "min_max_depth_in_subquery": [
                3,
                5
            ]
        },
        "1a0bdc86ca98295de2f50c46766742bd89fff524": {
            "meaningful_joins": "no",
            "table_exp_type": "FULL OUTER JOIN_INNER JOIN",
            "where_type": {
                "logical_operator": [
                    "OR",
                    "IN",
                    "pattern_matching"
                ]
            },
            "number_of_value_exp_in_group_by": 5,
            "having_type": "multiple",
            "orderby_type": "number_DESC",
            "limit_type": "with_offset",
            "value_exp_types": [
                "agg_exp_alias"
            ],
            "distinct_type": "none",
            "min_max_depth_in_subquery": [
                3,
                5
            ]
        },
        "e0f074aeb387d42eaf198ce854b8c7568931bae8": {
            "meaningful_joins": "mixed",
            "table_exp_type": "LEFT JOIN_RIGHT JOIN",
            "where_type": {
                "logical_operator": [
                    "OR",
                    "between",
                    "pattern_matching"
                ]
            },
            "number_of_value_exp_in_group_by": 4,
            "having_type": "multiple",
            "orderby_type": "multiple",
            "limit_type": "none",
            "value_exp_types": [
                "arithmatic_exp_alias"
            ],
            "distinct_type": "none",
            "min_max_depth_in_subquery": [
                3,
                5
            ]
        },
        "b7e7ce8027a28a20262ab1304f630698dacf72c3": {
            "meaningful_joins": "mixed",
            "table_exp_type": "FULL OUTER JOIN_LEFT JOIN",
            "where_type": {
                "logical_operator": [
                    "AND",
                    "basic_comparison",
                    "not_exists_subquery"
                ]
            },
            "number_of_value_exp_in_group_by": 4,
            "having_type": "single",
            "orderby_type": "DESC",
            "limit_type": "none",
            "value_exp_types": [
                "agg_exp_alias",
                "single_exp"
            ],
            "distinct_type": "none",
            "min_max_depth_in_subquery": [
                3,
                5
            ]
        },
        "ad0fecab915339c9b498aea74985ba3fc5ab85b6": {
            "meaningful_joins": "no",
            "table_exp_type": "INNER JOIN_RIGHT JOIN",
            "where_type": {
                "logical_operator": [
                    "OR",
                    "pattern_matching",
                    "not_exists_subquery"
                ]
            },
            "number_of_value_exp_in_group_by": 3,
            "having_type": "single",
            "orderby_type": "DESC",
            "limit_type": "none",
            "value_exp_types": [
                "alias_exp",
                "arithmatic_exp_alias"
            ],
            "distinct_type": "none",
            "min_max_depth_in_subquery": [
                3,
                5
            ]
        },
        "fe9d156eb42b25de013018e43bb4e123872d5052": {
            "meaningful_joins": "yes",
            "table_exp_type": "INNER JOIN_Join",
            "where_type": {
                "logical_operator": [
                    "OR",
                    "between",
                    "NOT IN"
                ]
            },
            "number_of_value_exp_in_group_by": 5,
            "having_type": "single",
            "orderby_type": "none",
            "limit_type": "none",
            "value_exp_types": [
                "alias_exp",
                "arithmatic_exp_alias"
            ],
            "distinct_type": "none",
            "min_max_depth_in_subquery": [
                3,
                5
            ]
        },
        "11f4080048715fa8d46ffd42c97ebfef72b5d77c": {
            "meaningful_joins": "yes",
            "table_exp_type": "INNER JOIN",
            "where_type": {
                "logical_operator": [
                    "AND",
                    "IN",
                    "basic_comparison"
                ]
            },
            "number_of_value_exp_in_group_by": 2,
            "having_type": "single",
            "orderby_type": "ASC",
            "limit_type": "none",
            "value_exp_types": [
                "agg_exp_alias",
                "count_distinct_exp"
            ],
            "distinct_type": "distinct",
            "min_max_depth_in_subquery": [
                3,
                5
            ]
        },
        "71cb2bca786ea7d45f737f77ba4f3fd7b1f28f00": {
            "meaningful_joins": "yes",
            "table_exp_type": "RIGHT JOIN",
            "where_type": {
                "logical_operator": [
                    "AND",
                    "between",
                    "basic_comparison"
                ]
            },
            "number_of_value_exp_in_group_by": 2,
            "having_type": "multiple",
            "orderby_type": "multiple",
            "limit_type": "with_offset",
            "value_exp_types": [
                "alias_exp",
                "count_distinct_exp"
            ],
            "distinct_type": "distinct",
            "min_max_depth_in_subquery": [
                3,
                5
            ]
        },
        "4cb2d5b409c1dea0e0b2e9d1779aadb427d42304": {
            "meaningful_joins": "no",
            "table_exp_type": "Join_Join",
            "where_type": {
                "logical_operator": [
                    "AND",
                    "basic_comparison",
                    "not_exists_subquery"
                ]
            },
            "number_of_value_exp_in_group_by": 0,
            "having_type": "none",
            "orderby_type": "multiple",
            "limit_type": "without_offset",
            "value_exp_types": [
                "arithmatic_exp",
                "count_distinct_exp"
            ],
            "distinct_type": "none",
            "min_max_depth_in_subquery": [
                3,
                5
            ]
        },
        "8522266c3f64d7c0780af011cf0e6edb6b5a26e9": {
            "meaningful_joins": "mixed",
            "table_exp_type": "single_table_with_name_changing",
            "where_type": {
                "logical_operator": [
                    "AND",
                    "basic_comparison",
                    "comparison_with_subquery"
                ]
            },
            "number_of_value_exp_in_group_by": 2,
            "having_type": "multiple",
            "orderby_type": "ASC",
            "limit_type": "with_offset",
            "value_exp_types": [
                "math_func_exp_alias",
                "string_func_exp"
            ],
            "distinct_type": "none",
            "min_max_depth_in_subquery": [
                3,
                5
            ]
        },
        "064c1501792239cc24a4a6bd1f19c8ebd5c0577c": {
            "meaningful_joins": "mixed",
            "table_exp_type": "Join_LEFT JOIN",
            "where_type": {
                "logical_operator": [
                    "OR",
                    "between",
                    "null_check"
                ]
            },
            "number_of_value_exp_in_group_by": 0,
            "having_type": "none",
            "orderby_type": "DESC",
            "limit_type": "without_offset",
            "value_exp_types": [
                "math_func_exp_alias",
                "single_exp"
            ],
            "distinct_type": "distinct",
            "min_max_depth_in_subquery": [
                3,
                5
            ]
        },
        "0419ee2d37b7666938d095f49e2fdf02ba3c7323": {
            "meaningful_joins": "yes",
            "table_exp_type": "Join",
            "where_type": {
                "logical_operator": [
                    "OR",
                    "IN",
                    "pattern_matching"
                ]
            },
            "number_of_value_exp_in_group_by": 0,
            "having_type": "none",
            "orderby_type": "ASC",
            "limit_type": "with_offset",
            "value_exp_types": [
                "agg_exp_alias",
                "arithmatic_exp_alias"
            ],
            "distinct_type": "none",
            "min_max_depth_in_subquery": [
                3,
                5
            ]
        },
        "779abd3098dcac2916f99c57b4eb8e318c5d5d05": {
            "meaningful_joins": "no",
            "table_exp_type": "Join_LEFT JOIN",
            "where_type": {
                "logical_operator": [
                    "AND",
                    "NOT IN",
                    "pattern_matching"
                ]
            },
            "number_of_value_exp_in_group_by": 5,
            "having_type": "multiple",
            "orderby_type": "number_DESC",
            "limit_type": "none",
            "value_exp_types": [
                "alias_exp",
                "math_func_exp_alias"
            ],
            "distinct_type": "distinct",
            "min_max_depth_in_subquery": [
                3,
                5
            ]
        },
        "adfd329328300bfc1fef0a2c58caa52bd4bdee38": {
            "meaningful_joins": "yes",
            "table_exp_type": "single_table_with_name_changing",
            "where_type": {
                "logical_operator": [
                    "AND",
                    "comparison_with_subquery",
                    "not_exists_subquery"
                ]
            },
            "number_of_value_exp_in_group_by": 1,
            "having_type": "multiple",
            "orderby_type": "DESC",
            "limit_type": "none",
            "value_exp_types": [
                "agg_exp_alias",
                "alias_exp"
            ],
            "distinct_type": "distinct",
            "min_max_depth_in_subquery": [
                3,
                5
            ]
        },
        "807f2ce27f577eb340954aece29d046e5ec6e984": {
            "meaningful_joins": "no",
            "table_exp_type": "LEFT JOIN_RIGHT JOIN",
            "where_type": {
                "logical_operator": [
                    "OR",
                    "pattern_matching",
                    "not_exists_subquery"
                ]
            },
            "number_of_value_exp_in_group_by": 1,
            "having_type": "none",
            "orderby_type": "ASC",
            "limit_type": "without_offset",
            "value_exp_types": [
                "math_func_exp_alias",
                "math_func_exp_alias"
            ],
            "distinct_type": "none",
            "min_max_depth_in_subquery": [
                3,
                5
            ]
        },
        "ac31d12a184efb11235f57ddc7c51f143681e762": {
            "meaningful_joins": "yes",
            "table_exp_type": "RIGHT JOIN",
            "where_type": {
                "logical_operator": [
                    "AND",
                    "pattern_matching",
                    "exists_subquery"
                ]
            },
            "number_of_value_exp_in_group_by": 2,
            "having_type": "multiple",
            "orderby_type": "DESC",
            "limit_type": "without_offset",
            "value_exp_types": [
                "arithmatic_exp",
                "math_func_exp_alias"
            ],
            "distinct_type": "none",
            "min_max_depth_in_subquery": [
                3,
                5
            ]
        },
        "24f2aa9034264f608bf7e84ed76d93ac13554449": {
            "meaningful_joins": "yes",
            "table_exp_type": "FULL OUTER JOIN_Join",
            "where_type": {
                "logical_operator": [
                    "AND",
                    "pattern_matching",
                    "exists_subquery"
                ]
            },
            "number_of_value_exp_in_group_by": 3,
            "having_type": "none",
            "orderby_type": "DESC",
            "limit_type": "with_offset",
            "value_exp_types": [
                "arithmatic_exp",
                "string_func_exp"
            ],
            "distinct_type": "none",
            "min_max_depth_in_subquery": [
                3,
                5
            ]
        },
        "07caebc5687f1fe461f6af7bc4ee374cb648178a": {
            "meaningful_joins": "mixed",
            "table_exp_type": "FULL OUTER JOIN_LEFT JOIN",
            "where_type": {
                "logical_operator": [
                    "AND",
                    "basic_comparison",
                    "not_exists_subquery"
                ]
            },
            "number_of_value_exp_in_group_by": 1,
            "having_type": "single",
            "orderby_type": "none",
            "limit_type": "with_offset",
            "value_exp_types": [
                "math_func_exp_alias",
                "math_func_exp_alias"
            ],
            "distinct_type": "distinct",
            "min_max_depth_in_subquery": [
                3,
                5
            ]
        },
        "643bbf92223d6e67a4c441948e97078e6c13c547": {
            "meaningful_joins": "mixed",
            "table_exp_type": "FULL OUTER JOIN_RIGHT JOIN",
            "where_type": {
                "logical_operator": [
                    "OR",
                    "between",
                    "null_check"
                ]
            },
            "number_of_value_exp_in_group_by": 4,
            "having_type": "none",
            "orderby_type": "number_ASC",
            "limit_type": "with_offset",
            "value_exp_types": [
                "agg_exp_alias",
                "string_func_exp"
            ],
            "distinct_type": "none",
            "min_max_depth_in_subquery": [
                3,
                5
            ]
        },
        "2e7ae27e2e59867d2d926b0462f6ee2b5e093349": {
            "meaningful_joins": "mixed",
            "table_exp_type": "Join_RIGHT JOIN",
            "where_type": {
                "logical_operator": [
                    "OR",
                    "basic_comparison",
                    "not_exists_subquery"
                ]
            },
            "number_of_value_exp_in_group_by": 3,
            "having_type": "single",
            "orderby_type": "none",
            "limit_type": "none",
            "value_exp_types": [
                "count_distinct_exp",
                "string_func_exp_alias"
            ],
            "distinct_type": "distinct",
            "min_max_depth_in_subquery": [
                3,
                5
            ]
        },
        "6f4af550c66c38cdf3e49b4d1ae56a3f0b9fcc4d": {
            "meaningful_joins": "mixed",
            "table_exp_type": "LEFT JOIN_LEFT JOIN",
            "where_type": {
                "logical_operator": [
                    "OR",
                    "pattern_matching",
                    "in_with_subquery"
                ]
            },
            "number_of_value_exp_in_group_by": 5,
            "having_type": "single",
            "orderby_type": "number_DESC",
            "limit_type": "none",
            "value_exp_types": [
                "string_func_exp",
                "string_func_exp_alias"
            ],
            "distinct_type": "distinct",
            "min_max_depth_in_subquery": [
                3,
                5
            ]
        },
        "772fcc85bd704548daa9f5b82bf607a1b566450c": {
            "meaningful_joins": "yes",
            "table_exp_type": "INNER JOIN_INNER JOIN",
            "where_type": {
                "logical_operator": [
                    "OR",
                    "between",
                    "pattern_matching"
                ]
            },
            "number_of_value_exp_in_group_by": 4,
            "having_type": "none",
            "orderby_type": "number_DESC",
            "limit_type": "without_offset",
            "value_exp_types": [
                "arithmatic_exp_alias",
                "string_func_exp_alias"
            ],
            "distinct_type": "distinct",
            "min_max_depth_in_subquery": [
                3,
                5
            ]
        },
        "ecf80cf691acebb560f7a72455e396486164c0a3": {
            "meaningful_joins": "yes",
            "table_exp_type": "LEFT JOIN",
            "where_type": {
                "logical_operator": [
                    "OR",
                    "pattern_matching",
                    "exists_subquery"
                ]
            },
            "number_of_value_exp_in_group_by": 2,
            "having_type": "single",
            "orderby_type": "ASC",
            "limit_type": "none",
            "value_exp_types": [
                "count_distinct_exp",
                "count_distinct_exp"
            ],
            "distinct_type": "none",
            "min_max_depth_in_subquery": [
                3,
                5
            ]
        },
        "aff84656226f915c2c22dfd11e0c087161a99348": {
            "meaningful_joins": "yes",
            "table_exp_type": "Join_LEFT JOIN",
            "where_type": {
                "logical_operator": [
                    "OR",
                    "pattern_matching",
                    "not_exists_subquery"
                ]
            },
            "number_of_value_exp_in_group_by": 0,
            "having_type": "none",
            "orderby_type": "none",
            "limit_type": "without_offset",
            "value_exp_types": [
                "alias_exp",
                "string_func_exp"
            ],
            "distinct_type": "distinct",
            "min_max_depth_in_subquery": [
                3,
                5
            ]
        },
        "04e1a7843b7ed4579010930d445041437198e1c6": {
            "meaningful_joins": "no",
            "table_exp_type": "single_table_with_name_changing",
            "where_type": {
                "logical_operator": [
                    "AND",
                    "pattern_matching",
                    "comparison_with_subquery"
                ]
            },
            "number_of_value_exp_in_group_by": 2,
            "having_type": "single",
            "orderby_type": "number_ASC",
            "limit_type": "with_offset",
            "value_exp_types": [
                "arithmatic_exp"
            ],
            "distinct_type": "distinct",
            "min_max_depth_in_subquery": [
                3,
                5
            ]
        },
        "4758e594a668abe5ef0a6344cdec3241329853b7": {
            "meaningful_joins": "no",
            "table_exp_type": "Join_Join",
            "where_type": {
                "logical_operator": [
                    "AND",
                    "basic_comparison",
                    "not_exists_subquery"
                ]
            },
            "number_of_value_exp_in_group_by": 1,
            "having_type": "single",
            "orderby_type": "DESC",
            "limit_type": "without_offset",
            "value_exp_types": [
                "alias_exp",
                "arithmatic_exp_alias"
            ],
            "distinct_type": "none",
            "min_max_depth_in_subquery": [
                3,
                5
            ]
        },
        "8e4d4029e64f035ea63b77256b77bd2f6a19603f": {
            "meaningful_joins": "no",
            "table_exp_type": "FULL OUTER JOIN_Join",
            "where_type": {
                "logical_operator": [
                    "AND",
                    "pattern_matching",
                    "not_exists_subquery"
                ]
            },
            "number_of_value_exp_in_group_by": 2,
            "having_type": "none",
            "orderby_type": "multiple",
            "limit_type": "none",
            "value_exp_types": [
                "count_distinct_exp"
            ],
            "distinct_type": "none",
            "min_max_depth_in_subquery": [
                3,
                5
            ]
        },
        "6f5b9869ce0f1f52b01e458d2b7e3173b2eb37a6": {
            "meaningful_joins": "yes",
            "table_exp_type": "LEFT JOIN_RIGHT JOIN",
            "where_type": {
                "logical_operator": [
                    "AND",
                    "comparison_with_subquery",
                    "not_exists_subquery"
                ]
            },
            "number_of_value_exp_in_group_by": 3,
            "having_type": "multiple",
            "orderby_type": "DESC",
            "limit_type": "with_offset",
            "value_exp_types": [
                "agg_exp_alias",
                "agg_exp_alias"
            ],
            "distinct_type": "distinct",
            "min_max_depth_in_subquery": [
                3,
                5
            ]
        },
        "6006ec0b0c6ca1431f61e824235331995ce1d814": {
            "meaningful_joins": "no",
            "table_exp_type": "FULL OUTER JOIN_Join",
            "where_type": {
                "logical_operator": [
                    "OR",
                    "NOT IN",
                    "pattern_matching"
                ]
            },
            "number_of_value_exp_in_group_by": 2,
            "having_type": "single",
            "orderby_type": "DESC",
            "limit_type": "without_offset",
            "value_exp_types": [
                "count_distinct_exp",
                "string_func_exp"
            ],
            "distinct_type": "none",
            "min_max_depth_in_subquery": [
                3,
                5
            ]
        },
        "e8b7ce08d8efa0fec78eee7e9dd9f7b7ddf8b611": {
            "meaningful_joins": "mixed",
            "table_exp_type": "LEFT JOIN_RIGHT JOIN",
            "where_type": {
                "logical_operator": [
                    "AND",
                    "pattern_matching",
                    "comparison_with_subquery"
                ]
            },
            "number_of_value_exp_in_group_by": 4,
            "having_type": "single",
            "orderby_type": "number_ASC",
            "limit_type": "with_offset",
            "value_exp_types": [
                "alias_exp",
                "alias_exp"
            ],
            "distinct_type": "none",
            "min_max_depth_in_subquery": [
                3,
                5
            ]
        },
        "1db042cb4836b13068edf3d36d2b556a8b6c418b": {
            "meaningful_joins": "mixed",
            "table_exp_type": "INNER JOIN",
            "where_type": {
                "logical_operator": [
                    "AND",
                    "pattern_matching",
                    "comparison_with_subquery"
                ]
            },
            "number_of_value_exp_in_group_by": 3,
            "having_type": "single",
            "orderby_type": "none",
            "limit_type": "without_offset",
            "value_exp_types": [
                "arithmatic_exp_alias",
                "string_func_exp"
            ],
            "distinct_type": "none",
            "min_max_depth_in_subquery": [
                3,
                5
            ]
        },
        "400e1046b843496a9a5b5f4d55088e713d76a1d8": {
            "meaningful_joins": "no",
            "table_exp_type": "FULL OUTER JOIN_INNER JOIN",
            "where_type": {
                "logical_operator": [
                    "OR",
                    "basic_comparison",
                    "comparison_with_subquery"
                ]
            },
            "number_of_value_exp_in_group_by": 1,
            "having_type": "single",
            "orderby_type": "none",
            "limit_type": "without_offset",
            "value_exp_types": [
                "count_distinct_exp",
                "math_func_exp_alias"
            ],
            "distinct_type": "distinct",
            "min_max_depth_in_subquery": [
                3,
                5
            ]
        },
        "81ca67b6b4b6c86a8fa10257f4b4530c29927c0d": {
            "meaningful_joins": "no",
            "table_exp_type": "Join_RIGHT JOIN",
            "where_type": {
                "logical_operator": [
                    "OR",
                    "basic_comparison",
                    "in_with_subquery"
                ]
            },
            "number_of_value_exp_in_group_by": 3,
            "having_type": "multiple",
            "orderby_type": "number_ASC",
            "limit_type": "none",
            "value_exp_types": [
                "arithmatic_exp",
                "arithmatic_exp"
            ],
            "distinct_type": "distinct",
            "min_max_depth_in_subquery": [
                3,
                5
            ]
        },
        "5ad444b0d985cbfb340a0eafaec940138ab4e419": {
            "meaningful_joins": "mixed",
            "table_exp_type": "INNER JOIN_LEFT JOIN",
            "where_type": {
                "logical_operator": [
                    "OR",
                    "pattern_matching",
                    "in_with_subquery"
                ]
            },
            "number_of_value_exp_in_group_by": 4,
            "having_type": "multiple",
            "orderby_type": "ASC",
            "limit_type": "none",
            "value_exp_types": [
                "string_func_exp"
            ],
            "distinct_type": "distinct",
            "min_max_depth_in_subquery": [
                3,
                5
            ]
        },
        "f34d00e1e3458c35c3f1da4856cc5d63eaf4d8b5": {
            "meaningful_joins": "mixed",
            "table_exp_type": "single_table_with_name_changing",
            "where_type": {
                "logical_operator": [
                    "AND",
                    "basic_comparison",
                    "exists_subquery"
                ]
            },
            "number_of_value_exp_in_group_by": 2,
            "having_type": "multiple",
            "orderby_type": "number_DESC",
            "limit_type": "without_offset",
            "value_exp_types": [
                "arithmatic_exp_alias",
                "arithmatic_exp_alias"
            ],
            "distinct_type": "none",
            "min_max_depth_in_subquery": [
                3,
                5
            ]
        },
        "f3c4a14e93bdbb4ec6da27084a6cc0d7a24ee59d": {
            "meaningful_joins": "mixed",
            "table_exp_type": "INNER JOIN_Join",
            "where_type": {
                "logical_operator": [
                    "AND",
                    "pattern_matching",
                    "exists_subquery"
                ]
            },
            "number_of_value_exp_in_group_by": 4,
            "having_type": "multiple",
            "orderby_type": "ASC",
            "limit_type": "without_offset",
            "value_exp_types": [
                "alias_exp",
                "string_func_exp_alias"
            ],
            "distinct_type": "none",
            "min_max_depth_in_subquery": [
                3,
                5
            ]
        },
        "7124d4404a57dfc25dbb108d8f7f49708c63bde8": {
            "meaningful_joins": "yes",
            "table_exp_type": "RIGHT JOIN_RIGHT JOIN",
            "where_type": {
                "logical_operator": [
                    "OR",
                    "pattern_matching",
                    "exists_subquery"
                ]
            },
            "number_of_value_exp_in_group_by": 4,
            "having_type": "none",
            "orderby_type": "multiple",
            "limit_type": "none",
            "value_exp_types": [
                "count_distinct_exp",
                "single_exp"
            ],
            "distinct_type": "none",
            "min_max_depth_in_subquery": [
                3,
                5
            ]
        },
        "0004217bc21f09c97dd5a0ced959ba10710985ea": {
            "meaningful_joins": "no",
            "table_exp_type": "INNER JOIN_LEFT JOIN",
            "where_type": "in_with_subquery",
            "number_of_value_exp_in_group_by": 4,
            "having_type": "multiple",
            "orderby_type": "ASC",
            "limit_type": "none",
            "value_exp_types": [
                "single_exp",
                "string_func_exp"
            ],
            "distinct_type": "distinct",
            "min_max_depth_in_subquery": [
                3,
                5
            ]
        },
        "99a47d62de2bc2f739a272eaff1299bf7d857b86": {
            "meaningful_joins": "yes",
            "table_exp_type": "FULL OUTER JOIN_RIGHT JOIN",
            "where_type": {
                "logical_operator": [
                    "AND",
                    "IN",
                    "basic_comparison"
                ]
            },
            "number_of_value_exp_in_group_by": 0,
            "having_type": "none",
            "orderby_type": "DESC",
            "limit_type": "with_offset",
            "value_exp_types": [
                "agg_exp_alias",
                "arithmatic_exp"
            ],
            "distinct_type": "none",
            "min_max_depth_in_subquery": [
                3,
                5
            ]
        },
        "e0e7cc2be1297a54ef20e08587d0601881e71b3f": {
            "meaningful_joins": "yes",
            "table_exp_type": "LEFT JOIN_LEFT JOIN",
            "where_type": {
                "logical_operator": [
                    "AND",
                    "between",
                    "basic_comparison"
                ]
            },
            "number_of_value_exp_in_group_by": 5,
            "having_type": "single",
            "orderby_type": "none",
            "limit_type": "none",
            "value_exp_types": [
                "string_func_exp",
                "string_func_exp_alias"
            ],
            "distinct_type": "none",
            "min_max_depth_in_subquery": [
                3,
                5
            ]
        },
        "4b9fcc4b7bd5ef06e5ae1cfb103843a78105c46f": {
            "meaningful_joins": "mixed",
            "table_exp_type": "INNER JOIN_LEFT JOIN",
            "where_type": {
                "logical_operator": [
                    "OR",
                    "pattern_matching",
                    "not_exists_subquery"
                ]
            },
            "number_of_value_exp_in_group_by": 1,
            "having_type": "none",
            "orderby_type": "DESC",
            "limit_type": "without_offset",
            "value_exp_types": [
                "agg_exp_alias",
                "arithmatic_exp_alias"
            ],
            "distinct_type": "none",
            "min_max_depth_in_subquery": [
                3,
                5
            ]
        },
        "5e02851c9c6d29e8579fdedb983b9c43ace371ed": {
            "meaningful_joins": "yes",
            "table_exp_type": "LEFT JOIN",
            "where_type": {
                "logical_operator": [
                    "AND",
                    "pattern_matching",
                    "in_with_subquery"
                ]
            },
            "number_of_value_exp_in_group_by": 1,
            "having_type": "none",
            "orderby_type": "ASC",
            "limit_type": "none",
            "value_exp_types": [
                "agg_exp_alias",
                "arithmatic_exp"
            ],
            "distinct_type": "none",
            "min_max_depth_in_subquery": [
                3,
                5
            ]
        },
        "ca04ed5a528f0d196b95b514e8352894d75d7519": {
            "meaningful_joins": "no",
            "table_exp_type": "LEFT JOIN_RIGHT JOIN",
            "where_type": {
                "logical_operator": [
                    "AND",
                    "pattern_matching",
                    "not_exists_subquery"
                ]
            },
            "number_of_value_exp_in_group_by": 0,
            "having_type": "none",
            "orderby_type": "none",
            "limit_type": "with_offset",
            "value_exp_types": [
                "arithmatic_exp_alias",
                "arithmatic_exp_alias"
            ],
            "distinct_type": "none",
            "min_max_depth_in_subquery": [
                3,
                5
            ]
        },
        "5e61c5f9d39905c8e7322cf49b27584a54426132": {
            "meaningful_joins": "no",
            "table_exp_type": "INNER JOIN_INNER JOIN",
            "where_type": {
                "logical_operator": [
                    "AND",
                    "IN",
                    "NOT IN"
                ]
            },
            "number_of_value_exp_in_group_by": 1,
            "having_type": "multiple",
            "orderby_type": "number_DESC",
            "limit_type": "without_offset",
            "value_exp_types": [
                "alias_exp",
                "count_distinct_exp"
            ],
            "distinct_type": "distinct",
            "min_max_depth_in_subquery": [
                3,
                5
            ]
        },
        "347daacee4bf0d202ab585bbd588bbc2f86e2b3c": {
            "meaningful_joins": "yes",
            "table_exp_type": "INNER JOIN_RIGHT JOIN",
            "where_type": {
                "logical_operator": [
                    "AND",
                    "pattern_matching",
                    "comparison_with_subquery"
                ]
            },
            "number_of_value_exp_in_group_by": 0,
            "having_type": "none",
            "orderby_type": "DESC",
            "limit_type": "with_offset",
            "value_exp_types": "*",
            "distinct_type": "distinct",
            "min_max_depth_in_subquery": [
                3,
                5
            ]
        },
        "7d2b78fd8e573164e51e99d65df2cdd2c2f8e8db": {
            "meaningful_joins": "mixed",
            "table_exp_type": "INNER JOIN",
            "where_type": {
                "logical_operator": [
                    "AND",
                    "between",
                    "pattern_matching"
                ]
            },
            "number_of_value_exp_in_group_by": 2,
            "having_type": "multiple",
            "orderby_type": "DESC",
            "limit_type": "without_offset",
            "value_exp_types": [
                "alias_exp"
            ],
            "distinct_type": "distinct",
            "min_max_depth_in_subquery": [
                3,
                5
            ]
        },
        "004cbaf126fe8f4c6dc5fd4028f35f2fc6a7492c": {
            "meaningful_joins": "no",
            "table_exp_type": "RIGHT JOIN_RIGHT JOIN",
            "where_type": {
                "logical_operator": [
                    "AND",
                    "NOT IN",
                    "comparison_with_subquery"
                ]
            },
            "number_of_value_exp_in_group_by": 3,
            "having_type": "multiple",
            "orderby_type": "none",
            "limit_type": "without_offset",
            "value_exp_types": [
                "string_func_exp_alias",
                "string_func_exp_alias"
            ],
            "distinct_type": "distinct",
            "min_max_depth_in_subquery": [
                3,
                5
            ]
        },
        "df67ed5b641db2a82e8247ab02a7d2b469324782": {
            "meaningful_joins": "yes",
            "table_exp_type": "INNER JOIN_LEFT JOIN",
            "where_type": {
                "pattern_matching": [
                    "NOT LIKE",
                    "exactly_5_characters"
                ]
            },
            "number_of_value_exp_in_group_by": 3,
            "having_type": "multiple",
            "orderby_type": "multiple",
            "limit_type": "none",
            "value_exp_types": [
                "alias_exp",
                "string_func_exp_alias"
            ],
            "distinct_type": "none",
            "min_max_depth_in_subquery": [
                3,
                5
            ]
        },
        "beb714bc82f6a49b84938476daa1164dabcc3f44": {
            "meaningful_joins": "yes",
            "table_exp_type": "Join",
            "where_type": {
                "logical_operator": [
                    "OR",
                    "null_check",
                    "comparison_with_subquery"
                ]
            },
            "number_of_value_exp_in_group_by": 1,
            "having_type": "multiple",
            "orderby_type": "number_DESC",
            "limit_type": "none",
            "value_exp_types": [
                "count_distinct_exp"
            ],
            "distinct_type": "distinct",
            "min_max_depth_in_subquery": [
                3,
                5
            ]
        },
        "d10652c6476afb5389fa895aa352321def67a241": {
            "meaningful_joins": "mixed",
            "table_exp_type": "LEFT JOIN_LEFT JOIN",
            "where_type": {
                "logical_operator": [
                    "OR",
                    "basic_comparison",
                    "exists_subquery"
                ]
            },
            "number_of_value_exp_in_group_by": 4,
            "having_type": "single",
            "orderby_type": "DESC",
            "limit_type": "without_offset",
            "value_exp_types": [
                "agg_exp_alias"
            ],
            "distinct_type": "distinct",
            "min_max_depth_in_subquery": [
                3,
                5
            ]
        },
        "ec89470747b7384ec29da9e558b31d3f1ec0184a": {
            "meaningful_joins": "yes",
            "table_exp_type": "INNER JOIN_INNER JOIN",
            "where_type": {
                "logical_operator": [
                    "OR",
                    "IN",
                    "comparison_with_subquery"
                ]
            },
            "number_of_value_exp_in_group_by": 3,
            "having_type": "single",
            "orderby_type": "ASC",
            "limit_type": "without_offset",
            "value_exp_types": [
                "arithmatic_exp_alias",
                "string_func_exp"
            ],
            "distinct_type": "distinct",
            "min_max_depth_in_subquery": [
                3,
                5
            ]
        },
        "ea956023fbaa123697c0d3bdaf93284e04e9e308": {
            "meaningful_joins": "yes",
            "table_exp_type": "INNER JOIN_Join",
            "where_type": {
                "logical_operator": [
                    "AND",
                    "pattern_matching",
                    "not_exists_subquery"
                ]
            },
            "number_of_value_exp_in_group_by": 2,
            "having_type": "single",
            "orderby_type": "ASC",
            "limit_type": "with_offset",
            "value_exp_types": [
                "arithmatic_exp_alias",
                "string_func_exp_alias"
            ],
            "distinct_type": "none",
            "min_max_depth_in_subquery": [
                3,
                5
            ]
        },
        "904599e3eea3c76a42de672b4703c316c4facbae": {
            "meaningful_joins": "no",
            "table_exp_type": "LEFT JOIN_LEFT JOIN",
            "where_type": {
                "logical_operator": [
                    "OR",
                    "null_check",
                    "not_exists_subquery"
                ]
            },
            "number_of_value_exp_in_group_by": 3,
            "having_type": "none",
            "orderby_type": "DESC",
            "limit_type": "without_offset",
            "value_exp_types": [
                "single_exp"
            ],
            "distinct_type": "none",
            "min_max_depth_in_subquery": [
                3,
                5
            ]
        },
        "34b5c8dc8f180cc14e030ff2cbc42d536d9a1f59": {
            "meaningful_joins": "mixed",
            "table_exp_type": "FULL OUTER JOIN_FULL OUTER JOIN",
            "where_type": {
                "logical_operator": [
                    "OR",
                    "between",
                    "basic_comparison"
                ]
            },
            "number_of_value_exp_in_group_by": 0,
            "having_type": "none",
            "orderby_type": "multiple",
            "limit_type": "none",
            "value_exp_types": [
                "agg_exp_alias",
                "count_distinct_exp"
            ],
            "distinct_type": "none",
            "min_max_depth_in_subquery": [
                3,
                5
            ]
        },
        "081fee10595761380246ecb781e1b3b48fd27bc6": {
            "meaningful_joins": "mixed",
            "table_exp_type": "FULL OUTER JOIN_INNER JOIN",
            "where_type": {
                "logical_operator": [
                    "AND",
                    "null_check",
                    "comparison_with_subquery"
                ]
            },
            "number_of_value_exp_in_group_by": 5,
            "having_type": "single",
            "orderby_type": "DESC",
            "limit_type": "with_offset",
            "value_exp_types": [
                "count_distinct_exp",
                "single_exp"
            ],
            "distinct_type": "distinct",
            "min_max_depth_in_subquery": [
                3,
                5
            ]
        },
        "347df5bc95c072301029bcad7abf98e91c4f52af": {
            "meaningful_joins": "no",
            "table_exp_type": "FULL OUTER JOIN_INNER JOIN",
            "where_type": {
                "logical_operator": [
                    "AND",
                    "null_check",
                    "comparison_with_subquery"
                ]
            },
            "number_of_value_exp_in_group_by": 1,
            "having_type": "none",
            "orderby_type": "ASC",
            "limit_type": "with_offset",
            "value_exp_types": [
                "arithmatic_exp",
                "count_distinct_exp"
            ],
            "distinct_type": "none",
            "min_max_depth_in_subquery": [
                3,
                5
            ]
        },
        "5a5554ca9414da9560afbb1866c1c5d42081eb2f": {
            "meaningful_joins": "no",
            "table_exp_type": "Join_LEFT JOIN",
            "where_type": {
                "logical_operator": [
                    "OR",
                    "null_check",
                    "not_exists_subquery"
                ]
            },
            "number_of_value_exp_in_group_by": 4,
            "having_type": "none",
            "orderby_type": "multiple",
            "limit_type": "without_offset",
            "value_exp_types": [
                "alias_exp",
                "string_func_exp"
            ],
            "distinct_type": "none",
            "min_max_depth_in_subquery": [
                3,
                5
            ]
        },
        "c9e9fd1617a9332b32c2e9754c34d4bb074e9a04": {
            "meaningful_joins": "yes",
            "table_exp_type": "LEFT JOIN_LEFT JOIN",
            "where_type": {
                "logical_operator": [
                    "AND",
                    "IN",
                    "pattern_matching"
                ]
            },
            "number_of_value_exp_in_group_by": 1,
            "having_type": "single",
            "orderby_type": "multiple",
            "limit_type": "with_offset",
            "value_exp_types": [
                "single_exp"
            ],
            "distinct_type": "none",
            "min_max_depth_in_subquery": [
                3,
                5
            ]
        },
        "b2b6e7c59d41fd0e7c56c59c22203b7ca2f1dfb8": {
            "meaningful_joins": "no",
            "table_exp_type": "Join_LEFT JOIN",
            "where_type": {
                "logical_operator": [
                    "OR",
                    "NOT IN",
                    "pattern_matching"
                ]
            },
            "number_of_value_exp_in_group_by": 5,
            "having_type": "single",
            "orderby_type": "number_ASC",
            "limit_type": "none",
            "value_exp_types": [
                "alias_exp",
                "arithmatic_exp_alias"
            ],
            "distinct_type": "distinct",
            "min_max_depth_in_subquery": [
                3,
                5
            ]
        },
        "278894568f2f398eabc6f353210e7fb6f1f01192": {
            "meaningful_joins": "no",
            "table_exp_type": "RIGHT JOIN",
            "where_type": {
                "logical_operator": [
                    "AND",
                    "IN",
                    "pattern_matching"
                ]
            },
            "number_of_value_exp_in_group_by": 4,
            "having_type": "multiple",
            "orderby_type": "multiple",
            "limit_type": "without_offset",
            "value_exp_types": [
                "agg_exp_alias",
                "single_exp"
            ],
            "distinct_type": "distinct",
            "min_max_depth_in_subquery": [
                3,
                5
            ]
        },
        "7282b5bf5edbfc770cf7e043524c8bd601feca11": {
            "meaningful_joins": "no",
            "table_exp_type": "FULL OUTER JOIN_LEFT JOIN",
            "where_type": {
                "logical_operator": [
                    "AND",
                    "basic_comparison",
                    "exists_subquery"
                ]
            },
            "number_of_value_exp_in_group_by": 5,
            "having_type": "none",
            "orderby_type": "number_ASC",
            "limit_type": "none",
            "value_exp_types": [
                "arithmatic_exp",
                "single_exp"
            ],
            "distinct_type": "none",
            "min_max_depth_in_subquery": [
                3,
                5
            ]
        },
        "b1c12e9417f26176a1b6578496e59ea600b929c7": {
            "meaningful_joins": "mixed",
            "table_exp_type": "RIGHT JOIN",
            "where_type": {
                "logical_operator": [
                    "OR",
                    "pattern_matching",
                    "in_with_subquery"
                ]
            },
            "number_of_value_exp_in_group_by": 1,
            "having_type": "none",
            "orderby_type": "none",
            "limit_type": "without_offset",
            "value_exp_types": [
                "agg_exp_alias",
                "arithmatic_exp_alias"
            ],
            "distinct_type": "distinct",
            "min_max_depth_in_subquery": [
                3,
                5
            ]
        },
        "3104f23e06881de431a737e42620f2ad75c2ce5b": {
            "meaningful_joins": "mixed",
            "table_exp_type": "FULL OUTER JOIN_LEFT JOIN",
            "where_type": {
                "logical_operator": [
                    "OR",
                    "IN",
                    "basic_comparison"
                ]
            },
            "number_of_value_exp_in_group_by": 3,
            "having_type": "multiple",
            "orderby_type": "ASC",
            "limit_type": "with_offset",
            "value_exp_types": [
                "string_func_exp",
                "string_func_exp"
            ],
            "distinct_type": "none",
            "min_max_depth_in_subquery": [
                3,
                5
            ]
        },
        "11078c912f0ee19c3b48473b30b1911c783ef9e0": {
            "meaningful_joins": "yes",
            "table_exp_type": "LEFT JOIN",
            "where_type": {
                "logical_operator": [
                    "AND",
                    "pattern_matching",
                    "comparison_with_subquery"
                ]
            },
            "number_of_value_exp_in_group_by": 1,
            "having_type": "multiple",
            "orderby_type": "none",
            "limit_type": "without_offset",
            "value_exp_types": [
                "arithmatic_exp"
            ],
            "distinct_type": "distinct",
            "min_max_depth_in_subquery": [
                3,
                5
            ]
        },
        "9cf5182e28589fe0f2f6ff2bf7cf5c44a42052cc": {
            "meaningful_joins": "yes",
            "table_exp_type": "INNER JOIN_RIGHT JOIN",
            "where_type": {
                "logical_operator": [
                    "OR",
                    "IN",
                    "exists_subquery"
                ]
            },
            "number_of_value_exp_in_group_by": 3,
            "having_type": "single",
            "orderby_type": "DESC",
            "limit_type": "none",
            "value_exp_types": [
                "count_distinct_exp",
                "string_func_exp"
            ],
            "distinct_type": "none",
            "min_max_depth_in_subquery": [
                3,
                5
            ]
        },
        "8f1f16b24614a2a41724b4d0b1d977673a4a5618": {
            "meaningful_joins": "no",
            "table_exp_type": "FULL OUTER JOIN",
            "where_type": {
                "logical_operator": [
                    "AND",
                    "null_check",
                    "comparison_with_subquery"
                ]
            },
            "number_of_value_exp_in_group_by": 5,
            "having_type": "none",
            "orderby_type": "number_ASC",
            "limit_type": "without_offset",
            "value_exp_types": [
                "arithmatic_exp_alias",
                "math_func_exp_alias"
            ],
            "distinct_type": "none",
            "min_max_depth_in_subquery": [
                3,
                5
            ]
        },
        "899cc11560d4fe9cdf6be31a30bd2c371986bb71": {
            "meaningful_joins": "no",
            "table_exp_type": "LEFT JOIN_RIGHT JOIN",
            "where_type": {
                "logical_operator": [
                    "AND",
                    "pattern_matching",
                    "not_exists_subquery"
                ]
            },
            "number_of_value_exp_in_group_by": 3,
            "having_type": "multiple",
            "orderby_type": "none",
            "limit_type": "none",
            "value_exp_types": [
                "alias_exp",
                "string_func_exp_alias"
            ],
            "distinct_type": "none",
            "min_max_depth_in_subquery": [
                3,
                5
            ]
        },
        "b153ca5518b548c7a2b6cf3c7168e4f6266d85a1": {
            "meaningful_joins": "mixed",
            "table_exp_type": "single_table_with_name_changing",
            "where_type": {
                "logical_operator": [
                    "AND",
                    "basic_comparison",
                    "comparison_with_subquery"
                ]
            },
            "number_of_value_exp_in_group_by": 4,
            "having_type": "multiple",
            "orderby_type": "number_DESC",
            "limit_type": "with_offset",
            "value_exp_types": [
                "count_distinct_exp",
                "math_func_exp_alias"
            ],
            "distinct_type": "none",
            "min_max_depth_in_subquery": [
                3,
                5
            ]
        },
        "37cee656cdb08dc488886b40601d50e755f72c07": {
            "meaningful_joins": "yes",
            "table_exp_type": "Join_LEFT JOIN",
            "where_type": {
                "logical_operator": [
                    "OR",
                    "NOT IN",
                    "pattern_matching"
                ]
            },
            "number_of_value_exp_in_group_by": 0,
            "having_type": "none",
            "orderby_type": "number_ASC",
            "limit_type": "with_offset",
            "value_exp_types": [
                "agg_exp_alias",
                "arithmatic_exp_alias"
            ],
            "distinct_type": "none",
            "min_max_depth_in_subquery": [
                3,
                5
            ]
        },
        "2e62daaa10cb09f6b212c52d097b69b35d4e11f3": {
            "meaningful_joins": "yes",
            "table_exp_type": "FULL OUTER JOIN_RIGHT JOIN",
            "where_type": {
                "logical_operator": [
                    "OR",
                    "between",
                    "basic_comparison"
                ]
            },
            "number_of_value_exp_in_group_by": 3,
            "having_type": "none",
            "orderby_type": "none",
            "limit_type": "without_offset",
            "value_exp_types": [
                "string_func_exp_alias"
            ],
            "distinct_type": "distinct",
            "min_max_depth_in_subquery": [
                3,
                5
            ]
        },
        "ba04c2ff3f86aef9e69fc405a0c9d3ff38580799": {
            "meaningful_joins": "mixed",
            "table_exp_type": "INNER JOIN_INNER JOIN",
            "where_type": {
                "logical_operator": [
                    "OR",
                    "NOT IN",
                    "in_with_subquery"
                ]
            },
            "number_of_value_exp_in_group_by": 4,
            "having_type": "none",
            "orderby_type": "number_ASC",
            "limit_type": "without_offset",
            "value_exp_types": [
                "string_func_exp"
            ],
            "distinct_type": "distinct",
            "min_max_depth_in_subquery": [
                3,
                5
            ]
        },
        "67cdff5ab25079eed0a63e957918e5d0600fbedd": {
            "meaningful_joins": "mixed",
            "table_exp_type": "LEFT JOIN",
            "where_type": {
                "logical_operator": [
                    "AND",
                    "NOT IN",
                    "basic_comparison"
                ]
            },
            "number_of_value_exp_in_group_by": 5,
            "having_type": "none",
            "orderby_type": "ASC",
            "limit_type": "none",
            "value_exp_types": [
                "agg_exp_alias",
                "single_exp"
            ],
            "distinct_type": "none",
            "min_max_depth_in_subquery": [
                3,
                5
            ]
        },
        "8543b854228cf1dc92bd164ed6f78968fcc8e2bd": {
            "meaningful_joins": "mixed",
            "table_exp_type": "FULL OUTER JOIN_FULL OUTER JOIN",
            "where_type": {
                "basic_comparison": "<="
            },
            "number_of_value_exp_in_group_by": 2,
            "having_type": "single",
            "orderby_type": "multiple",
            "limit_type": "none",
            "value_exp_types": [
                "arithmatic_exp_alias",
                "math_func_exp_alias"
            ],
            "distinct_type": "none",
            "min_max_depth_in_subquery": [
                3,
                5
            ]
        },
        "4c9626762d318cd9822804f0dbd42c80f7bcd601": {
            "meaningful_joins": "no",
            "table_exp_type": "FULL OUTER JOIN_INNER JOIN",
            "where_type": {
                "logical_operator": [
                    "OR",
                    "basic_comparison",
                    "exists_subquery"
                ]
            },
            "number_of_value_exp_in_group_by": 3,
            "having_type": "single",
            "orderby_type": "multiple",
            "limit_type": "none",
            "value_exp_types": [
                "count_distinct_exp"
            ],
            "distinct_type": "distinct",
            "min_max_depth_in_subquery": [
                3,
                5
            ]
        },
        "9121bf6ae80f1af6732a4c060e5d290c7aa73e73": {
            "meaningful_joins": "yes",
            "table_exp_type": "FULL OUTER JOIN_RIGHT JOIN",
            "where_type": {
                "logical_operator": [
                    "OR",
                    "pattern_matching",
                    "exists_subquery"
                ]
            },
            "number_of_value_exp_in_group_by": 3,
            "having_type": "none",
            "orderby_type": "none",
            "limit_type": "without_offset",
            "value_exp_types": [
                "agg_exp_alias",
                "arithmatic_exp"
            ],
            "distinct_type": "distinct",
            "min_max_depth_in_subquery": [
                3,
                5
            ]
        },
        "97fb777d3e2ed0e6af640d00224a23ed748a3c10": {
            "meaningful_joins": "no",
            "table_exp_type": "FULL OUTER JOIN_RIGHT JOIN",
            "where_type": {
                "logical_operator": [
                    "AND",
                    "NOT IN",
                    "pattern_matching"
                ]
            },
            "number_of_value_exp_in_group_by": 4,
            "having_type": "none",
            "orderby_type": "multiple",
            "limit_type": "none",
            "value_exp_types": [
                "alias_exp",
                "arithmatic_exp"
            ],
            "distinct_type": "distinct",
            "min_max_depth_in_subquery": [
                3,
                5
            ]
        },
        "affde296ed42ce69899386e6617c81c6bccc8dcc": {
            "meaningful_joins": "mixed",
            "table_exp_type": "FULL OUTER JOIN_INNER JOIN",
            "where_type": {
                "logical_operator": [
                    "AND",
                    "basic_comparison",
                    "not_exists_subquery"
                ]
            },
            "number_of_value_exp_in_group_by": 0,
            "having_type": "none",
            "orderby_type": "number_DESC",
            "limit_type": "without_offset",
            "value_exp_types": [
                "agg_exp_alias",
                "string_func_exp_alias"
            ],
            "distinct_type": "none",
            "min_max_depth_in_subquery": [
                3,
                5
            ]
        },
        "1f5ba234a86d29691db1ac5e0faf5687a499fbc9": {
            "meaningful_joins": "mixed",
            "table_exp_type": "Join_Join",
            "where_type": {
                "logical_operator": [
                    "AND",
                    "null_check",
                    "in_with_subquery"
                ]
            },
            "number_of_value_exp_in_group_by": 0,
            "having_type": "none",
            "orderby_type": "number_ASC",
            "limit_type": "with_offset",
            "value_exp_types": [
                "arithmatic_exp",
                "single_exp"
            ],
            "distinct_type": "none",
            "min_max_depth_in_subquery": [
                3,
                5
            ]
        },
        "3b66b28f5b715eef5300ad5b11f4e4106d7224e9": {
            "meaningful_joins": "mixed",
            "table_exp_type": "LEFT JOIN",
            "where_type": {
                "logical_operator": [
                    "OR",
                    "null_check",
                    "comparison_with_subquery"
                ]
            },
            "number_of_value_exp_in_group_by": 1,
            "having_type": "none",
            "orderby_type": "number_DESC",
            "limit_type": "none",
            "value_exp_types": [
                "arithmatic_exp",
                "count_distinct_exp"
            ],
            "distinct_type": "none",
            "min_max_depth_in_subquery": [
                3,
                5
            ]
        },
        "d95fc8c99adf35c7bc7c093916660b0810d7e0d6": {
            "meaningful_joins": "mixed",
            "table_exp_type": "INNER JOIN_INNER JOIN",
            "where_type": {
                "logical_operator": [
                    "OR",
                    "NOT IN",
                    "basic_comparison"
                ]
            },
            "number_of_value_exp_in_group_by": 1,
            "having_type": "none",
            "orderby_type": "ASC",
            "limit_type": "with_offset",
            "value_exp_types": [
                "arithmatic_exp",
                "count_distinct_exp"
            ],
            "distinct_type": "none",
            "min_max_depth_in_subquery": [
                3,
                5
            ]
        },
        "a389757a05a611a1d72a3a28495c52deb2393c2f": {
            "meaningful_joins": "no",
            "table_exp_type": "INNER JOIN_LEFT JOIN",
            "where_type": {
                "logical_operator": [
                    "AND",
                    "pattern_matching",
                    "not_exists_subquery"
                ]
            },
            "number_of_value_exp_in_group_by": 1,
            "having_type": "none",
            "orderby_type": "number_ASC",
            "limit_type": "without_offset",
            "value_exp_types": [
                "agg_exp_alias",
                "arithmatic_exp_alias"
            ],
            "distinct_type": "distinct",
            "min_max_depth_in_subquery": [
                3,
                5
            ]
        },
        "7ad92f046a098ce5b71158bbc3b761c16d600af4": {
            "meaningful_joins": "yes",
            "table_exp_type": "FULL OUTER JOIN_LEFT JOIN",
            "where_type": {
                "logical_operator": [
                    "OR",
                    "basic_comparison",
                    "not_exists_subquery"
                ]
            },
            "number_of_value_exp_in_group_by": 5,
            "having_type": "multiple",
            "orderby_type": "DESC",
            "limit_type": "none",
            "value_exp_types": [
                "string_func_exp",
                "string_func_exp"
            ],
            "distinct_type": "distinct",
            "min_max_depth_in_subquery": [
                3,
                5
            ]
        },
        "7938ca130cbc935fe40028a16cacbe47b227b439": {
            "meaningful_joins": "no",
            "table_exp_type": "LEFT JOIN_LEFT JOIN",
            "where_type": {
                "basic_comparison": ">"
            },
            "number_of_value_exp_in_group_by": 5,
            "having_type": "single",
            "orderby_type": "multiple",
            "limit_type": "without_offset",
            "value_exp_types": [
                "count_distinct_exp"
            ],
            "distinct_type": "distinct",
            "min_max_depth_in_subquery": [
                3,
                5
            ]
        },
        "c971b34d28b9742512b0b722cbc8f00b6c47f19d": {
            "meaningful_joins": "no",
            "table_exp_type": "INNER JOIN_Join",
            "where_type": {
                "logical_operator": [
                    "OR",
                    "basic_comparison",
                    "not_exists_subquery"
                ]
            },
            "number_of_value_exp_in_group_by": 3,
            "having_type": "multiple",
            "orderby_type": "none",
            "limit_type": "without_offset",
            "value_exp_types": [
                "count_distinct_exp",
                "single_exp"
            ],
            "distinct_type": "none",
            "min_max_depth_in_subquery": [
                3,
                5
            ]
        },
        "032e1883527d9d3e350beae10e88dd41c404d498": {
            "meaningful_joins": "mixed",
            "table_exp_type": "RIGHT JOIN_RIGHT JOIN",
            "where_type": {
                "logical_operator": [
                    "OR",
                    "NOT IN",
                    "pattern_matching"
                ]
            },
            "number_of_value_exp_in_group_by": 4,
            "having_type": "single",
            "orderby_type": "none",
            "limit_type": "with_offset",
            "value_exp_types": [
                "alias_exp",
                "arithmatic_exp_alias"
            ],
            "distinct_type": "none",
            "min_max_depth_in_subquery": [
                3,
                5
            ]
        },
        "639b0dffbf75523c79c289f43f514bafd097c40e": {
            "meaningful_joins": "mixed",
            "table_exp_type": "INNER JOIN_INNER JOIN",
            "where_type": {
                "logical_operator": [
                    "OR",
                    "basic_comparison",
                    "exists_subquery"
                ]
            },
            "number_of_value_exp_in_group_by": 1,
            "having_type": "single",
            "orderby_type": "DESC",
            "limit_type": "none",
            "value_exp_types": [
                "arithmatic_exp",
                "string_func_exp_alias"
            ],
            "distinct_type": "none",
            "min_max_depth_in_subquery": [
                3,
                5
            ]
        },
        "fba82aa9fb4d7fce9682ebf102a5130547520cea": {
            "meaningful_joins": "no",
            "table_exp_type": "FULL OUTER JOIN_INNER JOIN",
            "where_type": {
                "logical_operator": [
                    "OR",
                    "null_check",
                    "in_with_subquery"
                ]
            },
            "number_of_value_exp_in_group_by": 2,
            "having_type": "multiple",
            "orderby_type": "multiple",
            "limit_type": "with_offset",
            "value_exp_types": [
                "alias_exp"
            ],
            "distinct_type": "none",
            "min_max_depth_in_subquery": [
                3,
                5
            ]
        },
        "70329a72bb4368df3349507bea87bb24e6f09d66": {
            "meaningful_joins": "yes",
            "table_exp_type": "INNER JOIN_Join",
            "where_type": {
                "logical_operator": [
                    "AND",
                    "NOT IN",
                    "pattern_matching"
                ]
            },
            "number_of_value_exp_in_group_by": 5,
            "having_type": "multiple",
            "orderby_type": "DESC",
            "limit_type": "none",
            "value_exp_types": [
                "single_exp",
                "string_func_exp"
            ],
            "distinct_type": "distinct",
            "min_max_depth_in_subquery": [
                3,
                5
            ]
        },
        "bfe46b1cd6647e6cb9890084613257abbebca395": {
            "meaningful_joins": "yes",
            "table_exp_type": "FULL OUTER JOIN_FULL OUTER JOIN",
            "where_type": {
                "logical_operator": [
                    "OR",
                    "pattern_matching",
                    "in_with_subquery"
                ]
            },
            "number_of_value_exp_in_group_by": 1,
            "having_type": "none",
            "orderby_type": "number_DESC",
            "limit_type": "without_offset",
            "value_exp_types": [
                "math_func_exp_alias",
                "single_exp"
            ],
            "distinct_type": "distinct",
            "min_max_depth_in_subquery": [
                3,
                5
            ]
        },
        "672dc034feb3b04543592c803268dc9da6a86156": {
            "meaningful_joins": "no",
            "table_exp_type": "LEFT JOIN_RIGHT JOIN",
            "where_type": {
                "logical_operator": [
                    "OR",
                    "basic_comparison",
                    "exists_subquery"
                ]
            },
            "number_of_value_exp_in_group_by": 1,
            "having_type": "none",
            "orderby_type": "number_DESC",
            "limit_type": "none",
            "value_exp_types": [
                "string_func_exp"
            ],
            "distinct_type": "none",
            "min_max_depth_in_subquery": [
                3,
                5
            ]
        },
        "5912ef8ec21456c2018a5abe86dfa2c62e76a7f3": {
            "meaningful_joins": "mixed",
            "table_exp_type": "single_table_with_name_changing",
            "where_type": {
                "logical_operator": [
                    "OR",
                    "pattern_matching",
                    "not_exists_subquery"
                ]
            },
            "number_of_value_exp_in_group_by": 0,
            "having_type": "none",
            "orderby_type": "number_ASC",
            "limit_type": "with_offset",
            "value_exp_types": [
                "string_func_exp",
                "string_func_exp"
            ],
            "distinct_type": "none",
            "min_max_depth_in_subquery": [
                3,
                5
            ]
        },
        "3dcfd6d96760725e0193bb1605327cb4b5e59556": {
            "meaningful_joins": "mixed",
            "table_exp_type": "INNER JOIN_INNER JOIN",
            "where_type": {
                "logical_operator": [
                    "AND",
                    "not_exists_subquery",
                    "exists_subquery"
                ]
            },
            "number_of_value_exp_in_group_by": 3,
            "having_type": "single",
            "orderby_type": "ASC",
            "limit_type": "none",
            "value_exp_types": [
                "alias_exp"
            ],
            "distinct_type": "none",
            "min_max_depth_in_subquery": [
                3,
                5
            ]
        },
        "eaf8a8b9ff838945fcc96c8cc7325395a11c9e21": {
            "meaningful_joins": "yes",
            "table_exp_type": "Join_Join",
            "where_type": {
                "logical_operator": [
                    "AND",
                    "basic_comparison",
                    "not_exists_subquery"
                ]
            },
            "number_of_value_exp_in_group_by": 2,
            "having_type": "multiple",
            "orderby_type": "DESC",
            "limit_type": "without_offset",
            "value_exp_types": [
                "arithmatic_exp",
                "arithmatic_exp"
            ],
            "distinct_type": "distinct",
            "min_max_depth_in_subquery": [
                3,
                5
            ]
        },
        "097182ed9b45b3afc0786397563a5e001b937b85": {
            "meaningful_joins": "no",
            "table_exp_type": "LEFT JOIN_LEFT JOIN",
            "where_type": {
                "logical_operator": [
                    "OR",
                    "NOT IN",
                    "basic_comparison"
                ]
            },
            "number_of_value_exp_in_group_by": 4,
            "having_type": "single",
            "orderby_type": "multiple",
            "limit_type": "none",
            "value_exp_types": [
                "string_func_exp"
            ],
            "distinct_type": "none",
            "min_max_depth_in_subquery": [
                3,
                5
            ]
        },
        "acdb66e36d2512cd249f590ba3942527f6e76472": {
            "meaningful_joins": "yes",
            "table_exp_type": "RIGHT JOIN",
            "where_type": {
                "logical_operator": [
                    "AND",
                    "NOT IN",
                    "basic_comparison"
                ]
            },
            "number_of_value_exp_in_group_by": 5,
            "having_type": "multiple",
            "orderby_type": "ASC",
            "limit_type": "none",
            "value_exp_types": [
                "arithmatic_exp",
                "arithmatic_exp_alias"
            ],
            "distinct_type": "none",
            "min_max_depth_in_subquery": [
                3,
                5
            ]
        },
        "5ce9e2ee13de69acecc64a114371c241c046a326": {
            "meaningful_joins": "no",
            "table_exp_type": "single_table",
            "where_type": {
                "logical_operator": [
                    "OR",
                    "between",
                    "basic_comparison"
                ]
            },
            "number_of_value_exp_in_group_by": 2,
            "having_type": "multiple",
            "orderby_type": "DESC",
            "limit_type": "without_offset",
            "value_exp_types": [
                "single_exp",
                "string_func_exp"
            ],
            "distinct_type": "distinct",
            "min_max_depth_in_subquery": [
                3,
                5
            ]
        }
    }
}