{
    "farm": {
        "515c002ef17fa4a99dacd0d7e27a6d16cf6da655": {
            "set_op_type": "none",
            "first_query": {
                "meaningful_joins": "no",
                "table_exp_type": "Join_Join_RIGHT JOIN",
                "where_type": {
                    "logical_operator": [
                        "AND",
                        "basic_comparison",
                        "exists_subquery"
                    ]
                },
                "number_of_value_exp_in_group_by": 0,
                "having_type": "none",
                "orderby_type": "multiple",
                "limit_type": "with_offset",
                "value_exp_types": [
                    "arithmatic_exp",
                    "single_exp_text"
                ],
                "distinct_type": "none",
                "min_max_depth_in_subquery": [
                    3,
                    5
                ]
            }
        },
        "ec2063af9d7cf8020f4f3791f02df439a1e745d1": {
            "set_op_type": "none",
            "first_query": {
                "meaningful_joins": "mixed",
                "table_exp_type": "FULL OUTER JOIN_FULL OUTER JOIN_INNER JOIN",
                "where_type": {
                    "logical_operator": [
                        "OR",
                        "comparison_with_subquery",
                        "not_exists_subquery"
                    ]
                },
                "number_of_value_exp_in_group_by": 1,
                "having_type": {
                    "single": "COUNT DISTINCT"
                },
                "orderby_type": "number_DESC",
                "limit_type": "with_offset",
                "value_exp_types": [
                    "arithmatic_exp_alias",
                    "count_distinct_exp"
                ],
                "distinct_type": "distinct",
                "min_max_depth_in_subquery": [
                    3,
                    5
                ]
            }
        },
        "1a30e0b0e7a9be1483f5f4b069da6d183f8fd741": {
            "set_op_type": "none",
            "first_query": {
                "meaningful_joins": "mixed",
                "table_exp_type": "LEFT JOIN_RIGHT JOIN",
                "where_type": {
                    "logical_operator": [
                        "AND",
                        "between",
                        "basic_comparison"
                    ]
                },
                "number_of_value_exp_in_group_by": 5,
                "having_type": "none",
                "orderby_type": "none",
                "limit_type": "none",
                "value_exp_types": [
                    "alias_exp",
                    "string_func_exp"
                ],
                "distinct_type": "distinct",
                "min_max_depth_in_subquery": [
                    3,
                    5
                ]
            }
        },
        "6e83cced596ea9db5e4e7e13a99779c118ca9ff7": {
            "set_op_type": "none",
            "first_query": {
                "meaningful_joins": "no",
                "table_exp_type": "FULL OUTER JOIN_Join_Join",
                "where_type": {
                    "logical_operator": [
                        "OR",
                        "NOT IN",
                        "null_check"
                    ]
                },
                "number_of_value_exp_in_group_by": 2,
                "having_type": "multiple",
                "orderby_type": "none",
                "limit_type": "without_offset",
                "value_exp_types": [
                    "single_exp_number",
                    "single_exp_text"
                ],
                "distinct_type": "distinct",
                "min_max_depth_in_subquery": [
                    3,
                    5
                ]
            }
        },
        "5baf478ea68eb87cfe9f7ab5e54dd24479182e19": {
            "set_op_type": "none",
            "first_query": {
                "meaningful_joins": "yes",
                "table_exp_type": "FULL OUTER JOIN_RIGHT JOIN",
                "where_type": {
                    "basic_comparison": ">="
                },
                "number_of_value_exp_in_group_by": 4,
                "having_type": "not_exists_subquery",
                "orderby_type": "number_ASC",
                "limit_type": "with_offset",
                "value_exp_types": [
                    "string_func_exp_alias",
                    "string_func_exp_alias"
                ],
                "distinct_type": "distinct",
                "min_max_depth_in_subquery": [
                    3,
                    5
                ]
            }
        },
        "2159d02071123b9cb05c2b029aa4e76925e67422": {
            "set_op_type": "none",
            "first_query": {
                "meaningful_joins": "no",
                "table_exp_type": "INNER JOIN_Join",
                "where_type": {
                    "logical_operator": [
                        "OR",
                        "IN",
                        "comparison_with_subquery"
                    ]
                },
                "number_of_value_exp_in_group_by": 4,
                "having_type": "in_with_subquery",
                "orderby_type": "ASC",
                "limit_type": "without_offset",
                "value_exp_types": [
                    "arithmatic_exp_alias"
                ],
                "distinct_type": "none",
                "min_max_depth_in_subquery": [
                    3,
                    5
                ]
            }
        },
        "06ca3f674a275c051d184b074279bf6805d5832e": {
            "set_op_type": "none",
            "first_query": {
                "meaningful_joins": "mixed",
                "table_exp_type": "INNER JOIN_LEFT JOIN",
                "where_type": {
                    "logical_operator": [
                        "AND",
                        "pattern_matching",
                        "in_with_subquery"
                    ]
                },
                "number_of_value_exp_in_group_by": 0,
                "having_type": "none",
                "orderby_type": "DESC",
                "limit_type": "none",
                "value_exp_types": [
                    "arithmatic_exp"
                ],
                "distinct_type": "distinct",
                "min_max_depth_in_subquery": [
                    3,
                    5
                ]
            }
        },
        "d0f6186c51be01ec8c84f9ff635c0b7dff2c15cb": {
            "set_op_type": "none",
            "first_query": {
                "meaningful_joins": "no",
                "table_exp_type": "FULL OUTER JOIN_Join_Join",
                "where_type": {
                    "logical_operator": [
                        "AND",
                        "basic_comparison",
                        "exists_subquery"
                    ]
                },
                "number_of_value_exp_in_group_by": 2,
                "having_type": {
                    "single": "SUM"
                },
                "orderby_type": "multiple",
                "limit_type": "without_offset",
                "value_exp_types": [
                    "string_func_exp",
                    "string_func_exp"
                ],
                "distinct_type": "distinct",
                "min_max_depth_in_subquery": [
                    3,
                    5
                ]
            }
        },
        "13f9353a2c9fe525656d0e62c843de0eaa3c5afb": {
            "set_op_type": "none",
            "first_query": {
                "meaningful_joins": "no",
                "table_exp_type": "RIGHT JOIN_RIGHT JOIN_RIGHT JOIN",
                "where_type": {
                    "logical_operator": [
                        "OR",
                        "null_check",
                        "exists_subquery"
                    ]
                },
                "number_of_value_exp_in_group_by": 4,
                "having_type": "multiple",
                "orderby_type": "none",
                "limit_type": "none",
                "value_exp_types": [
                    "arithmatic_exp_alias",
                    "single_exp"
                ],
                "distinct_type": "distinct",
                "min_max_depth_in_subquery": [
                    3,
                    5
                ]
            }
        },
        "3a2534e1e69d89cfcf5cd2e98028c50ecbae632e": {
            "set_op_type": "none",
            "first_query": {
                "meaningful_joins": "no",
                "table_exp_type": "FULL OUTER JOIN_INNER JOIN_INNER JOIN",
                "where_type": {
                    "logical_operator": [
                        "AND",
                        "NOT IN",
                        "basic_comparison"
                    ]
                },
                "number_of_value_exp_in_group_by": 5,
                "having_type": "not_exists_subquery",
                "orderby_type": "DESC",
                "limit_type": "with_offset",
                "value_exp_types": [
                    "single_exp_number",
                    "string_func_exp"
                ],
                "distinct_type": "none",
                "min_max_depth_in_subquery": [
                    3,
                    5
                ]
            }
        },
        "77ccae60ed829e688959225c123b84458a5c9694": {
            "set_op_type": "none",
            "first_query": {
                "meaningful_joins": "yes",
                "table_exp_type": "Join_Join",
                "where_type": {
                    "logical_operator": [
                        "AND",
                        "IN",
                        "pattern_matching"
                    ]
                },
                "number_of_value_exp_in_group_by": 5,
                "having_type": "not_exists_subquery",
                "orderby_type": "ASC",
                "limit_type": "without_offset",
                "value_exp_types": [
                    "arithmatic_exp"
                ],
                "distinct_type": "none",
                "min_max_depth_in_subquery": [
                    3,
                    5
                ]
            }
        },
        "3098769bd7fe47d71118f34da3d982f035d63b73": {
            "set_op_type": "none",
            "first_query": {
                "meaningful_joins": "mixed",
                "table_exp_type": "single_table_with_name_changing",
                "where_type": {
                    "logical_operator": [
                        "OR",
                        "IN",
                        "comparison_with_subquery"
                    ]
                },
                "number_of_value_exp_in_group_by": 2,
                "having_type": "comparison_with_subquery",
                "orderby_type": "none",
                "limit_type": "none",
                "value_exp_types": [
                    "agg_exp_alias",
                    "arithmatic_exp"
                ],
                "distinct_type": "distinct",
                "min_max_depth_in_subquery": [
                    3,
                    5
                ]
            }
        },
        "46f6516aa881f08831c54e5cda474f11cecbbc8d": {
            "set_op_type": "none",
            "first_query": {
                "meaningful_joins": "mixed",
                "table_exp_type": "Join_RIGHT JOIN",
                "where_type": {
                    "logical_operator": [
                        "AND",
                        "NOT IN",
                        "basic_comparison"
                    ]
                },
                "number_of_value_exp_in_group_by": 1,
                "having_type": "multiple",
                "orderby_type": "ASC",
                "limit_type": "without_offset",
                "value_exp_types": "*",
                "distinct_type": "distinct",
                "min_max_depth_in_subquery": [
                    3,
                    5
                ]
            }
        },
        "5dca279039060e06b024e37097fcb65f1bb8b71f": {
            "set_op_type": "none",
            "first_query": {
                "meaningful_joins": "no",
                "table_exp_type": "INNER JOIN_Join_RIGHT JOIN",
                "where_type": {
                    "basic_comparison": "!="
                },
                "number_of_value_exp_in_group_by": 0,
                "having_type": "none",
                "orderby_type": "number_ASC",
                "limit_type": "with_offset",
                "value_exp_types": [
                    "single_exp_number"
                ],
                "distinct_type": "distinct",
                "min_max_depth_in_subquery": [
                    3,
                    5
                ]
            }
        },
        "edc0c05c99e29a5ff4ac942ce5c792c59f886009": {
            "set_op_type": "none",
            "first_query": {
                "meaningful_joins": "no",
                "table_exp_type": "INNER JOIN_Join_LEFT JOIN",
                "where_type": {
                    "logical_operator": [
                        "OR",
                        "pattern_matching",
                        "in_with_subquery"
                    ]
                },
                "number_of_value_exp_in_group_by": 0,
                "having_type": "none",
                "orderby_type": "multiple",
                "limit_type": "with_offset",
                "value_exp_types": [
                    "agg_exp_alias",
                    "count_distinct_exp"
                ],
                "distinct_type": "distinct",
                "min_max_depth_in_subquery": [
                    3,
                    5
                ]
            }
        },
        "502827b7384a91c67d5a8ab98f0158eaa3c8cf55": {
            "set_op_type": "none",
            "first_query": {
                "meaningful_joins": "yes",
                "table_exp_type": "FULL OUTER JOIN_INNER JOIN_Join",
                "where_type": {
                    "logical_operator": [
                        "AND",
                        "between",
                        "in_with_subquery"
                    ]
                },
                "number_of_value_exp_in_group_by": 5,
                "having_type": {
                    "single": "AVG"
                },
                "orderby_type": "ASC",
                "limit_type": "with_offset",
                "value_exp_types": [
                    "agg_exp_alias",
                    "arithmatic_exp"
                ],
                "distinct_type": "distinct",
                "min_max_depth_in_subquery": [
                    3,
                    5
                ]
            }
        },
        "fc9043d91bdc158ace0e91c3391374f564357aa9": {
            "set_op_type": "none",
            "first_query": {
                "meaningful_joins": "mixed",
                "table_exp_type": "Join_LEFT JOIN_RIGHT JOIN",
                "where_type": {
                    "logical_operator": [
                        "AND",
                        "pattern_matching",
                        "exists_subquery"
                    ]
                },
                "number_of_value_exp_in_group_by": 0,
                "having_type": "none",
                "orderby_type": "ASC",
                "limit_type": "with_offset",
                "value_exp_types": [
                    "agg_exp_alias",
                    "count_distinct_exp"
                ],
                "distinct_type": "none",
                "min_max_depth_in_subquery": [
                    3,
                    5
                ]
            }
        },
        "1ecdc5142f945029f8d329572de6e505037e0410": {
            "set_op_type": "none",
            "first_query": {
                "meaningful_joins": "mixed",
                "table_exp_type": "FULL OUTER JOIN_FULL OUTER JOIN_RIGHT JOIN",
                "where_type": {
                    "logical_operator": [
                        "OR",
                        "between",
                        "pattern_matching"
                    ]
                },
                "number_of_value_exp_in_group_by": 1,
                "having_type": "multiple",
                "orderby_type": "multiple",
                "limit_type": "without_offset",
                "value_exp_types": [
                    "alias_exp",
                    "arithmatic_exp"
                ],
                "distinct_type": "distinct",
                "min_max_depth_in_subquery": [
                    3,
                    5
                ]
            }
        },
        "da263c75ab84fc1e194f6a461f7748156d6bc827": {
            "set_op_type": "none",
            "first_query": {
                "meaningful_joins": "yes",
                "table_exp_type": "FULL OUTER JOIN_FULL OUTER JOIN_FULL OUTER JOIN",
                "where_type": {
                    "logical_operator": [
                        "AND",
                        "basic_comparison",
                        "not_exists_subquery"
                    ]
                },
                "number_of_value_exp_in_group_by": 3,
                "having_type": {
                    "single": "COUNT"
                },
                "orderby_type": "multiple",
                "limit_type": "with_offset",
                "value_exp_types": [
                    "agg_exp_alias",
                    "string_func_exp"
                ],
                "distinct_type": "none",
                "min_max_depth_in_subquery": [
                    3,
                    5
                ]
            }
        },
        "3f6a639a21a53d14afb8a7fe7f4fe8e788a95028": {
            "set_op_type": "none",
            "first_query": {
                "meaningful_joins": "no",
                "table_exp_type": "FULL OUTER JOIN_FULL OUTER JOIN_LEFT JOIN",
                "where_type": {
                    "logical_operator": [
                        "AND",
                        "NOT IN",
                        "null_check"
                    ]
                },
                "number_of_value_exp_in_group_by": 5,
                "having_type": "not_exists_subquery",
                "orderby_type": "number_ASC",
                "limit_type": "none",
                "value_exp_types": [
                    "arithmatic_exp",
                    "single_exp"
                ],
                "distinct_type": "distinct",
                "min_max_depth_in_subquery": [
                    3,
                    5
                ]
            }
        },
        "92be0a3db66ff07c9dd6d4f054a84e3ea3480b5e": {
            "set_op_type": "none",
            "first_query": {
                "meaningful_joins": "no",
                "table_exp_type": "FULL OUTER JOIN_INNER JOIN_LEFT JOIN",
                "where_type": {
                    "logical_operator": [
                        "OR",
                        "IN",
                        "basic_comparison"
                    ]
                },
                "number_of_value_exp_in_group_by": 5,
                "having_type": {
                    "single": "AVG"
                },
                "orderby_type": "number_ASC",
                "limit_type": "none",
                "value_exp_types": [
                    "agg_exp_alias"
                ],
                "distinct_type": "none",
                "min_max_depth_in_subquery": [
                    3,
                    5
                ]
            }
        },
        "4234374d823e29bb406e91bbaba465d9846afa4a": {
            "set_op_type": "none",
            "first_query": {
                "meaningful_joins": "yes",
                "table_exp_type": "LEFT JOIN",
                "where_type": {
                    "logical_operator": [
                        "AND",
                        "basic_comparison",
                        "not_exists_subquery"
                    ]
                },
                "number_of_value_exp_in_group_by": 2,
                "having_type": {
                    "single": "COUNT DISTINCT"
                },
                "orderby_type": "number_ASC",
                "limit_type": "without_offset",
                "value_exp_types": [
                    "arithmatic_exp_alias",
                    "arithmatic_exp_alias"
                ],
                "distinct_type": "none",
                "min_max_depth_in_subquery": [
                    3,
                    5
                ]
            }
        },
        "4d5a7b7b00a816c559dcab27b6ab8c98af8942fa": {
            "set_op_type": "none",
            "first_query": {
                "meaningful_joins": "mixed",
                "table_exp_type": "INNER JOIN_LEFT JOIN_LEFT JOIN",
                "where_type": {
                    "logical_operator": [
                        "OR",
                        "pattern_matching",
                        "comparison_with_subquery"
                    ]
                },
                "number_of_value_exp_in_group_by": 2,
                "having_type": "not_exists_subquery",
                "orderby_type": "multiple",
                "limit_type": "with_offset",
                "value_exp_types": [
                    "alias_exp",
                    "arithmatic_exp_alias"
                ],
                "distinct_type": "distinct",
                "min_max_depth_in_subquery": [
                    3,
                    5
                ]
            }
        },
        "5ca2afd37096a1145a0f8f5f993100c1b953ce03": {
            "set_op_type": "none",
            "first_query": {
                "meaningful_joins": "no",
                "table_exp_type": "INNER JOIN",
                "where_type": {
                    "logical_operator": [
                        "OR",
                        "pattern_matching",
                        "exists_subquery"
                    ]
                },
                "number_of_value_exp_in_group_by": 2,
                "having_type": {
                    "single": "COUNT DISTINCT"
                },
                "orderby_type": "DESC",
                "limit_type": "none",
                "value_exp_types": [
                    "alias_exp",
                    "single_exp"
                ],
                "distinct_type": "none",
                "min_max_depth_in_subquery": [
                    3,
                    5
                ]
            }
        },
        "bb4959f21dee5fa5945e6b0e365c9325a187faca": {
            "set_op_type": "none",
            "first_query": {
                "meaningful_joins": "mixed",
                "table_exp_type": "RIGHT JOIN",
                "where_type": {
                    "logical_operator": [
                        "OR",
                        "pattern_matching",
                        "comparison_with_subquery"
                    ]
                },
                "number_of_value_exp_in_group_by": 5,
                "having_type": "comparison_with_subquery",
                "orderby_type": "DESC",
                "limit_type": "none",
                "value_exp_types": [
                    "single_exp_number"
                ],
                "distinct_type": "distinct",
                "min_max_depth_in_subquery": [
                    3,
                    5
                ]
            }
        },
        "0ad210ca7ca1edde0decb1787080e796d42704fa": {
            "set_op_type": "none",
            "first_query": {
                "meaningful_joins": "mixed",
                "table_exp_type": "INNER JOIN_RIGHT JOIN_RIGHT JOIN",
                "where_type": {
                    "logical_operator": [
                        "OR",
                        "NOT IN",
                        "comparison_with_subquery"
                    ]
                },
                "number_of_value_exp_in_group_by": 2,
                "having_type": "not_exists_subquery",
                "orderby_type": "number_DESC",
                "limit_type": "with_offset",
                "value_exp_types": [
                    "single_exp_number",
                    "single_exp_number"
                ],
                "distinct_type": "none",
                "min_max_depth_in_subquery": [
                    3,
                    5
                ]
            }
        },
        "7b56d233789af431bee39865ac45f0c792b53df4": {
            "set_op_type": "none",
            "first_query": {
                "meaningful_joins": "yes",
                "table_exp_type": "INNER JOIN_Join_RIGHT JOIN",
                "where_type": {
                    "logical_operator": [
                        "OR",
                        "basic_comparison",
                        "in_with_subquery"
                    ]
                },
                "number_of_value_exp_in_group_by": 2,
                "having_type": {
                    "single": "COUNT"
                },
                "orderby_type": "number_ASC",
                "limit_type": "none",
                "value_exp_types": [
                    "single_exp_text",
                    "single_exp_text"
                ],
                "distinct_type": "none",
                "min_max_depth_in_subquery": [
                    3,
                    5
                ]
            }
        },
        "fecac9536b73f4e2ad107173a758418472048ec2": {
            "set_op_type": "none",
            "first_query": {
                "meaningful_joins": "mixed",
                "table_exp_type": "INNER JOIN_LEFT JOIN",
                "where_type": {
                    "logical_operator": [
                        "AND",
                        "NOT IN",
                        "null_check"
                    ]
                },
                "number_of_value_exp_in_group_by": 1,
                "having_type": "comparison_with_subquery",
                "orderby_type": "number_ASC",
                "limit_type": "without_offset",
                "value_exp_types": [
                    "count_distinct_exp",
                    "single_exp_text"
                ],
                "distinct_type": "distinct",
                "min_max_depth_in_subquery": [
                    3,
                    5
                ]
            }
        },
        "6506476bbac8842381d7355173fd7cd7995a8ffb": {
            "set_op_type": "none",
            "first_query": {
                "meaningful_joins": "mixed",
                "table_exp_type": "LEFT JOIN_LEFT JOIN_RIGHT JOIN",
                "where_type": {
                    "logical_operator": [
                        "AND",
                        "null_check",
                        "exists_subquery"
                    ]
                },
                "number_of_value_exp_in_group_by": 1,
                "having_type": {
                    "single": "SUM"
                },
                "orderby_type": "none",
                "limit_type": "without_offset",
                "value_exp_types": [
                    "arithmatic_exp_alias",
                    "single_exp_number"
                ],
                "distinct_type": "distinct",
                "min_max_depth_in_subquery": [
                    3,
                    5
                ]
            }
        },
        "03c2d914561502766fd5a0871bd094b3ec714340": {
            "set_op_type": "none",
            "first_query": {
                "meaningful_joins": "no",
                "table_exp_type": "INNER JOIN_Join_RIGHT JOIN",
                "where_type": {
                    "logical_operator": [
                        "OR",
                        "pattern_matching",
                        "exists_subquery"
                    ]
                },
                "number_of_value_exp_in_group_by": 4,
                "having_type": {
                    "single": "MIN"
                },
                "orderby_type": "number_DESC",
                "limit_type": "with_offset",
                "value_exp_types": [
                    "arithmatic_exp",
                    "arithmatic_exp"
                ],
                "distinct_type": "none",
                "min_max_depth_in_subquery": [
                    3,
                    5
                ]
            }
        },
        "4ae2fddae73bf8a2388cc1e0baf6367ec55b4480": {
            "set_op_type": "none",
            "first_query": {
                "meaningful_joins": "yes",
                "table_exp_type": "INNER JOIN_Join_RIGHT JOIN",
                "where_type": {
                    "logical_operator": [
                        "AND",
                        "NOT IN",
                        "comparison_with_subquery"
                    ]
                },
                "number_of_value_exp_in_group_by": 2,
                "having_type": "multiple",
                "orderby_type": "none",
                "limit_type": "without_offset",
                "value_exp_types": [
                    "arithmatic_exp",
                    "arithmatic_exp_alias"
                ],
                "distinct_type": "none",
                "min_max_depth_in_subquery": [
                    3,
                    5
                ]
            }
        },
        "73b3d2c798cdb7a2b0dc098bd72ed0792fb57fe6": {
            "set_op_type": "none",
            "first_query": {
                "meaningful_joins": "mixed",
                "table_exp_type": "INNER JOIN_Join_RIGHT JOIN",
                "where_type": {
                    "logical_operator": [
                        "AND",
                        "pattern_matching",
                        "in_with_subquery"
                    ]
                },
                "number_of_value_exp_in_group_by": 5,
                "having_type": {
                    "single": "AVG"
                },
                "orderby_type": "number_DESC",
                "limit_type": "none",
                "value_exp_types": [
                    "count_distinct_exp",
                    "string_func_exp_alias"
                ],
                "distinct_type": "none",
                "min_max_depth_in_subquery": [
                    3,
                    5
                ]
            }
        },
        "2b4f6e3e4fbb9b387715839b3ad06f81e7bdf71a": {
            "set_op_type": "none",
            "first_query": {
                "meaningful_joins": "yes",
                "table_exp_type": "FULL OUTER JOIN_INNER JOIN",
                "where_type": {
                    "logical_operator": [
                        "AND",
                        "basic_comparison",
                        "comparison_with_subquery"
                    ]
                },
                "number_of_value_exp_in_group_by": 5,
                "having_type": "multiple",
                "orderby_type": "number_DESC",
                "limit_type": "none",
                "value_exp_types": [
                    "single_exp_number",
                    "string_func_exp"
                ],
                "distinct_type": "distinct",
                "min_max_depth_in_subquery": [
                    3,
                    5
                ]
            }
        },
        "4e4a30d2991464e78af89c218a0febada3a7dfc5": {
            "set_op_type": "none",
            "first_query": {
                "meaningful_joins": "yes",
                "table_exp_type": "INNER JOIN_INNER JOIN_LEFT JOIN",
                "where_type": {
                    "logical_operator": [
                        "AND",
                        "basic_comparison",
                        "in_with_subquery"
                    ]
                },
                "number_of_value_exp_in_group_by": 3,
                "having_type": "comparison_with_subquery",
                "orderby_type": "multiple",
                "limit_type": "none",
                "value_exp_types": [
                    "string_func_exp_alias",
                    "string_func_exp_alias"
                ],
                "distinct_type": "none",
                "min_max_depth_in_subquery": [
                    3,
                    5
                ]
            }
        },
        "78f597797076fa76cfa68a4feaacac3ffa5bbc29": {
            "set_op_type": "none",
            "first_query": {
                "meaningful_joins": "mixed",
                "table_exp_type": "FULL OUTER JOIN_LEFT JOIN_LEFT JOIN",
                "where_type": {
                    "logical_operator": [
                        "OR",
                        "pattern_matching",
                        "comparison_with_subquery"
                    ]
                },
                "number_of_value_exp_in_group_by": 0,
                "having_type": "none",
                "orderby_type": "number_ASC",
                "limit_type": "without_offset",
                "value_exp_types": [
                    "single_exp_text",
                    "string_func_exp_alias"
                ],
                "distinct_type": "none",
                "min_max_depth_in_subquery": [
                    3,
                    5
                ]
            }
        },
        "7b9e5d07ac41ac585fa4cabd880d381fb7731293": {
            "set_op_type": "none",
            "first_query": {
                "meaningful_joins": "mixed",
                "table_exp_type": "FULL OUTER JOIN_FULL OUTER JOIN_LEFT JOIN",
                "where_type": {
                    "logical_operator": [
                        "OR",
                        "between",
                        "IN"
                    ]
                },
                "number_of_value_exp_in_group_by": 1,
                "having_type": {
                    "single": "MIN"
                },
                "orderby_type": "multiple",
                "limit_type": "with_offset",
                "value_exp_types": [
                    "string_func_exp_alias",
                    "string_func_exp_alias"
                ],
                "distinct_type": "distinct",
                "min_max_depth_in_subquery": [
                    3,
                    5
                ]
            }
        },
        "3d0f4f6b73b1cf08d2f9720250b525c4ac178eac": {
            "set_op_type": "none",
            "first_query": {
                "meaningful_joins": "mixed",
                "table_exp_type": "FULL OUTER JOIN_INNER JOIN_RIGHT JOIN",
                "where_type": "between",
                "number_of_value_exp_in_group_by": 2,
                "having_type": {
                    "single": "MAX"
                },
                "orderby_type": "number_ASC",
                "limit_type": "none",
                "value_exp_types": [
                    "count_distinct_exp"
                ],
                "distinct_type": "none",
                "min_max_depth_in_subquery": [
                    3,
                    5
                ]
            }
        },
        "9d0de24b647c875ef9b2cd7bbaa25b6969fcbb65": {
            "set_op_type": "none",
            "first_query": {
                "meaningful_joins": "mixed",
                "table_exp_type": "INNER JOIN_RIGHT JOIN_RIGHT JOIN",
                "where_type": {
                    "logical_operator": [
                        "OR",
                        "pattern_matching",
                        "not_exists_subquery"
                    ]
                },
                "number_of_value_exp_in_group_by": 1,
                "having_type": "none",
                "orderby_type": "DESC",
                "limit_type": "none",
                "value_exp_types": [
                    "string_func_exp"
                ],
                "distinct_type": "distinct",
                "min_max_depth_in_subquery": [
                    3,
                    5
                ]
            }
        },
        "8ea575e4d9a1167c74679f7f77a47cb8030a812f": {
            "set_op_type": "none",
            "first_query": {
                "meaningful_joins": "mixed",
                "table_exp_type": "INNER JOIN_INNER JOIN_Join",
                "where_type": {
                    "logical_operator": [
                        "OR",
                        "basic_comparison",
                        "comparison_with_subquery"
                    ]
                },
                "number_of_value_exp_in_group_by": 5,
                "having_type": {
                    "single": "AVG"
                },
                "orderby_type": "number_ASC",
                "limit_type": "none",
                "value_exp_types": [
                    "single_exp_number",
                    "string_func_exp"
                ],
                "distinct_type": "distinct",
                "min_max_depth_in_subquery": [
                    3,
                    5
                ]
            }
        },
        "c03dd133a859bc04e81895200f120711f37b9ad3": {
            "set_op_type": "none",
            "first_query": {
                "meaningful_joins": "no",
                "table_exp_type": "FULL OUTER JOIN",
                "where_type": {
                    "logical_operator": [
                        "OR",
                        "IN",
                        "pattern_matching"
                    ]
                },
                "number_of_value_exp_in_group_by": 2,
                "having_type": {
                    "single": "COUNT"
                },
                "orderby_type": "number_DESC",
                "limit_type": "without_offset",
                "value_exp_types": [
                    "agg_exp_alias",
                    "count_distinct_exp"
                ],
                "distinct_type": "distinct",
                "min_max_depth_in_subquery": [
                    3,
                    5
                ]
            }
        },
        "4525c2a044ef6f535951dd52571fb7a3e5460f49": {
            "set_op_type": "none",
            "first_query": {
                "meaningful_joins": "no",
                "table_exp_type": "single_table",
                "where_type": {
                    "logical_operator": [
                        "AND",
                        "NOT IN",
                        "basic_comparison"
                    ]
                },
                "number_of_value_exp_in_group_by": 0,
                "having_type": "none",
                "orderby_type": "ASC",
                "limit_type": "without_offset",
                "value_exp_types": [
                    "single_exp_number",
                    "string_func_exp_alias"
                ],
                "distinct_type": "none",
                "min_max_depth_in_subquery": [
                    3,
                    5
                ]
            }
        },
        "60e9b3ca27726aecc37ce38599f16e400d957ebd": {
            "set_op_type": "none",
            "first_query": {
                "meaningful_joins": "no",
                "table_exp_type": "RIGHT JOIN_RIGHT JOIN",
                "where_type": {
                    "logical_operator": [
                        "AND",
                        "IN",
                        "pattern_matching"
                    ]
                },
                "number_of_value_exp_in_group_by": 4,
                "having_type": {
                    "single": "AVG"
                },
                "orderby_type": "number_DESC",
                "limit_type": "none",
                "value_exp_types": [
                    "arithmatic_exp_alias",
                    "count_distinct_exp"
                ],
                "distinct_type": "none",
                "min_max_depth_in_subquery": [
                    3,
                    5
                ]
            }
        },
        "86050839d1d3df4b52081711e579cc16a4265e57": {
            "set_op_type": "none",
            "first_query": {
                "meaningful_joins": "yes",
                "table_exp_type": "LEFT JOIN_RIGHT JOIN_RIGHT JOIN",
                "where_type": {
                    "logical_operator": [
                        "AND",
                        "IN",
                        "not_exists_subquery"
                    ]
                },
                "number_of_value_exp_in_group_by": 4,
                "having_type": {
                    "single": "AVG"
                },
                "orderby_type": "none",
                "limit_type": "with_offset",
                "value_exp_types": [
                    "string_func_exp"
                ],
                "distinct_type": "none",
                "min_max_depth_in_subquery": [
                    3,
                    5
                ]
            }
        },
        "15beb8e438ff2399c19a3197033bdc1ac75a7ae9": {
            "set_op_type": "none",
            "first_query": {
                "meaningful_joins": "mixed",
                "table_exp_type": "INNER JOIN_LEFT JOIN_RIGHT JOIN",
                "where_type": "comparison_with_subquery",
                "number_of_value_exp_in_group_by": 5,
                "having_type": {
                    "single": "MAX"
                },
                "orderby_type": "number_DESC",
                "limit_type": "without_offset",
                "value_exp_types": [
                    "agg_exp_alias",
                    "alias_exp"
                ],
                "distinct_type": "none",
                "min_max_depth_in_subquery": [
                    3,
                    5
                ]
            }
        },
        "ce1adead0ec8e98d6b206f4959f2044aa70bc797": {
            "set_op_type": "none",
            "first_query": {
                "meaningful_joins": "mixed",
                "table_exp_type": "LEFT JOIN_RIGHT JOIN",
                "where_type": {
                    "logical_operator": [
                        "AND",
                        "IN",
                        "basic_comparison"
                    ]
                },
                "number_of_value_exp_in_group_by": 1,
                "having_type": {
                    "single": "SUM"
                },
                "orderby_type": "none",
                "limit_type": "with_offset",
                "value_exp_types": [
                    "single_exp_text",
                    "single_exp_text"
                ],
                "distinct_type": "none",
                "min_max_depth_in_subquery": [
                    3,
                    5
                ]
            }
        },
        "3ff49a6f344cdd48c96eeac2ed1025dd7d14df9f": {
            "set_op_type": "none",
            "first_query": {
                "meaningful_joins": "no",
                "table_exp_type": "INNER JOIN_LEFT JOIN_RIGHT JOIN",
                "where_type": {
                    "logical_operator": [
                        "OR",
                        "between",
                        "comparison_with_subquery"
                    ]
                },
                "number_of_value_exp_in_group_by": 5,
                "having_type": {
                    "single": "MAX"
                },
                "orderby_type": "number_DESC",
                "limit_type": "without_offset",
                "value_exp_types": [
                    "arithmatic_exp",
                    "string_func_exp_alias"
                ],
                "distinct_type": "distinct",
                "min_max_depth_in_subquery": [
                    3,
                    5
                ]
            }
        },
        "cd8be2c9e8b1c00b595c8fef70b59f0903b9c59e": {
            "set_op_type": "none",
            "first_query": {
                "meaningful_joins": "mixed",
                "table_exp_type": "INNER JOIN_INNER JOIN_Join",
                "where_type": {
                    "pattern_matching": [
                        "NOT LIKE",
                        "ends_with_ing"
                    ]
                },
                "number_of_value_exp_in_group_by": 2,
                "having_type": "none",
                "orderby_type": "number_DESC",
                "limit_type": "without_offset",
                "value_exp_types": [
                    "alias_exp"
                ],
                "distinct_type": "distinct",
                "min_max_depth_in_subquery": [
                    3,
                    5
                ]
            }
        },
        "8bb011aec34b073cef3e80aa570553eceeabe487": {
            "set_op_type": "none",
            "first_query": {
                "meaningful_joins": "no",
                "table_exp_type": "Join",
                "where_type": {
                    "logical_operator": [
                        "AND",
                        "IN",
                        "not_exists_subquery"
                    ]
                },
                "number_of_value_exp_in_group_by": 0,
                "having_type": "none",
                "orderby_type": "number_ASC",
                "limit_type": "with_offset",
                "value_exp_types": [
                    "count_distinct_exp",
                    "single_exp_number"
                ],
                "distinct_type": "distinct",
                "min_max_depth_in_subquery": [
                    3,
                    5
                ]
            }
        },
        "6eabfcefa5595c9e4438c9cb74fa621261688626": {
            "set_op_type": "none",
            "first_query": {
                "meaningful_joins": "yes",
                "table_exp_type": "LEFT JOIN_LEFT JOIN",
                "where_type": {
                    "logical_operator": [
                        "AND",
                        "basic_comparison",
                        "comparison_with_subquery"
                    ]
                },
                "number_of_value_exp_in_group_by": 4,
                "having_type": {
                    "single": "COUNT"
                },
                "orderby_type": "DESC",
                "limit_type": "with_offset",
                "value_exp_types": [
                    "single_exp_text",
                    "string_func_exp"
                ],
                "distinct_type": "none",
                "min_max_depth_in_subquery": [
                    3,
                    5
                ]
            }
        },
        "4e66791d4ba41d5fada3a4d3ac64a0c8eb8b7225": {
            "set_op_type": "none",
            "first_query": {
                "meaningful_joins": "mixed",
                "table_exp_type": "INNER JOIN_RIGHT JOIN",
                "where_type": {
                    "logical_operator": [
                        "AND",
                        "in_with_subquery",
                        "comparison_with_subquery"
                    ]
                },
                "number_of_value_exp_in_group_by": 2,
                "having_type": {
                    "single": "COUNT DISTINCT"
                },
                "orderby_type": "number_ASC",
                "limit_type": "with_offset",
                "value_exp_types": [
                    "agg_exp_alias",
                    "string_func_exp"
                ],
                "distinct_type": "none",
                "min_max_depth_in_subquery": [
                    3,
                    5
                ]
            }
        },
        "bddcd770d7d23d872f6b371c7aa236ccf2dc57d8": {
            "set_op_type": "none",
            "first_query": {
                "meaningful_joins": "yes",
                "table_exp_type": "INNER JOIN_LEFT JOIN_LEFT JOIN",
                "where_type": {
                    "logical_operator": [
                        "OR",
                        "basic_comparison",
                        "comparison_with_subquery"
                    ]
                },
                "number_of_value_exp_in_group_by": 4,
                "having_type": {
                    "single": "COUNT"
                },
                "orderby_type": "DESC",
                "limit_type": "without_offset",
                "value_exp_types": [
                    "single_exp",
                    "string_func_exp"
                ],
                "distinct_type": "none",
                "min_max_depth_in_subquery": [
                    3,
                    5
                ]
            }
        },
        "c89e030a84b37c8810589dd075fc9f6150e28049": {
            "set_op_type": "none",
            "first_query": {
                "meaningful_joins": "no",
                "table_exp_type": "INNER JOIN_LEFT JOIN",
                "where_type": {
                    "logical_operator": [
                        "AND",
                        "null_check",
                        "exists_subquery"
                    ]
                },
                "number_of_value_exp_in_group_by": 5,
                "having_type": {
                    "single": "COUNT"
                },
                "orderby_type": "DESC",
                "limit_type": "with_offset",
                "value_exp_types": [
                    "arithmatic_exp",
                    "string_func_exp_alias"
                ],
                "distinct_type": "none",
                "min_max_depth_in_subquery": [
                    3,
                    5
                ]
            }
        },
        "b4c427b13bd73f7750dd45e01e0f7631c6b41a59": {
            "set_op_type": "none",
            "first_query": {
                "meaningful_joins": "yes",
                "table_exp_type": "FULL OUTER JOIN_LEFT JOIN_RIGHT JOIN",
                "where_type": {
                    "logical_operator": [
                        "OR",
                        "pattern_matching",
                        "in_with_subquery"
                    ]
                },
                "number_of_value_exp_in_group_by": 3,
                "having_type": {
                    "single": "MIN"
                },
                "orderby_type": "multiple",
                "limit_type": "none",
                "value_exp_types": [
                    "arithmatic_exp_alias",
                    "single_exp_text"
                ],
                "distinct_type": "none",
                "min_max_depth_in_subquery": [
                    3,
                    5
                ]
            }
        },
        "74f38b258c764d2241533d25da3e166e959bd36c": {
            "set_op_type": "none",
            "first_query": {
                "meaningful_joins": "mixed",
                "table_exp_type": "INNER JOIN_LEFT JOIN",
                "where_type": {
                    "logical_operator": [
                        "AND",
                        "basic_comparison",
                        "not_exists_subquery"
                    ]
                },
                "number_of_value_exp_in_group_by": 0,
                "having_type": "none",
                "orderby_type": "number_ASC",
                "limit_type": "without_offset",
                "value_exp_types": [
                    "single_exp",
                    "string_func_exp_alias"
                ],
                "distinct_type": "distinct",
                "min_max_depth_in_subquery": [
                    3,
                    5
                ]
            }
        },
        "0f7c754e21bb24839ca983c123ac5fefbf003827": {
            "set_op_type": "none",
            "first_query": {
                "meaningful_joins": "yes",
                "table_exp_type": "FULL OUTER JOIN_FULL OUTER JOIN_RIGHT JOIN",
                "where_type": {
                    "logical_operator": [
                        "AND",
                        "IN",
                        "basic_comparison"
                    ]
                },
                "number_of_value_exp_in_group_by": 0,
                "having_type": "none",
                "orderby_type": "number_DESC",
                "limit_type": "with_offset",
                "value_exp_types": [
                    "agg_exp_alias",
                    "single_exp_text"
                ],
                "distinct_type": "distinct",
                "min_max_depth_in_subquery": [
                    3,
                    5
                ]
            }
        }
    }
}